{
  "scope": "state_house",
  "contest_type": "auditor",
  "year": 2010,
  "general": {
    "results": {
      "1": {
        "dem_votes": 0,
        "rep_votes": 0,
        "other_votes": 29430,
        "total_votes": 29430,
        "dem_candidate": "",
        "rep_candidate": "",
        "margin": 0,
        "margin_pct": 0.0,
        "winner": "TIE",
        "color": "#d9d9d9"
      },
      "2": {
        "dem_votes": 0,
        "rep_votes": 0,
        "other_votes": 21426,
        "total_votes": 21426,
        "dem_candidate": "",
        "rep_candidate": "",
        "margin": 0,
        "margin_pct": 0.0,
        "winner": "TIE",
        "color": "#d9d9d9"
      },
      "3": {
        "dem_votes": 0,
        "rep_votes": 0,
        "other_votes": 40873,
        "total_votes": 40873,
        "dem_candidate": "",
        "rep_candidate": "",
        "margin": 0,
        "margin_pct": 0.0,
        "winner": "TIE",
        "color": "#d9d9d9"
      },
      "4": {
        "dem_votes": 0,
        "rep_votes": 0,
        "other_votes": 25152,
        "total_votes": 25152,
        "dem_candidate": "",
        "rep_candidate": "",
        "margin": 0,
        "margin_pct": 0.0,
        "winner": "TIE",
        "color": "#d9d9d9"
      },
      "5": {
        "dem_votes": 0,
        "rep_votes": 0,
        "other_votes": 26120,
        "total_votes": 26120,
        "dem_candidate": "",
        "rep_candidate": "",
        "margin": 0,
        "margin_pct": 0.0,
        "winner": "TIE",
        "color": "#d9d9d9"
      },
      "6": {
        "dem_votes": 0,
        "rep_votes": 0,
        "other_votes": 47544,
        "total_votes": 47544,
        "dem_candidate": "",
        "rep_candidate": "",
        "margin": 0,
        "margin_pct": 0.0,
        "winner": "TIE",
        "color": "#d9d9d9"
      },
      "7": {
        "dem_votes": 0,
        "rep_votes": 0,
        "other_votes": 37867,
        "total_votes": 37867,
        "dem_candidate": "",
        "rep_candidate": "",
        "margin": 0,
        "margin_pct": 0.0,
        "winner": "TIE",
        "color": "#d9d9d9"
      },
      "8": {
        "dem_votes": 0,
        "rep_votes": 0,
        "other_votes": 33471,
        "total_votes": 33471,
        "dem_candidate": "",
        "rep_candidate": "",
        "margin": 0,
        "margin_pct": 0.0,
        "winner": "TIE",
        "color": "#d9d9d9"
      },
      "9": {
        "dem_votes": 0,
        "rep_votes": 0,
        "other_votes": 39433,
        "total_votes": 39433,
        "dem_candidate": "",
        "rep_candidate": "",
        "margin": 0,
        "margin_pct": 0.0,
        "winner": "TIE",
        "color": "#d9d9d9"
      },
      "10": {
        "dem_votes": 0,
        "rep_votes": 0,
        "other_votes": 22156,
        "total_votes": 22156,
        "dem_candidate": "",
        "rep_candidate": "",
        "margin": 0,
        "margin_pct": 0.0,
        "winner": "TIE",
        "color": "#d9d9d9"
      },
      "11": {
        "dem_votes": 0,
        "rep_votes": 0,
        "other_votes": 25693,
        "total_votes": 25693,
        "dem_candidate": "",
        "rep_candidate": "",
        "margin": 0,
        "margin_pct": 0.0,
        "winner": "TIE",
        "color": "#d9d9d9"
      },
      "12": {
        "dem_votes": 0,
        "rep_votes": 0,
        "other_votes": 35508,
        "total_votes": 35508,
        "dem_candidate": "",
        "rep_candidate": "",
        "margin": 0,
        "margin_pct": 0.0,
        "winner": "TIE",
        "color": "#d9d9d9"
      },
      "13": {
        "dem_votes": 0,
        "rep_votes": 0,
        "other_votes": 21219,
        "total_votes": 21219,
        "dem_candidate": "",
        "rep_candidate": "",
        "margin": 0,
        "margin_pct": 0.0,
        "winner": "TIE",
        "color": "#d9d9d9"
      },
      "14": {
        "dem_votes": 0,
        "rep_votes": 0,
        "other_votes": 31567,
        "total_votes": 31567,
        "dem_candidate": "",
        "rep_candidate": "",
        "margin": 0,
        "margin_pct": 0.0,
        "winner": "TIE",
        "color": "#d9d9d9"
      },
      "15": {
        "dem_votes": 0,
        "rep_votes": 0,
        "other_votes": 28706,
        "total_votes": 28706,
        "dem_candidate": "",
        "rep_candidate": "",
        "margin": 0,
        "margin_pct": 0.0,
        "winner": "TIE",
        "color": "#d9d9d9"
      },
      "16": {
        "dem_votes": 0,
        "rep_votes": 0,
        "other_votes": 41773,
        "total_votes": 41773,
        "dem_candidate": "",
        "rep_candidate": "",
        "margin": 0,
        "margin_pct": 0.0,
        "winner": "TIE",
        "color": "#d9d9d9"
      },
      "17": {
        "dem_votes": 0,
        "rep_votes": 0,
        "other_votes": 24774,
        "total_votes": 24774,
        "dem_candidate": "",
        "rep_candidate": "",
        "margin": 0,
        "margin_pct": 0.0,
        "winner": "TIE",
        "color": "#d9d9d9"
      },
      "18": {
        "dem_votes": 0,
        "rep_votes": 0,
        "other_votes": 29198,
        "total_votes": 29198,
        "dem_candidate": "",
        "rep_candidate": "",
        "margin": 0,
        "margin_pct": 0.0,
        "winner": "TIE",
        "color": "#d9d9d9"
      },
      "19": {
        "dem_votes": 0,
        "rep_votes": 0,
        "other_votes": 45249,
        "total_votes": 45249,
        "dem_candidate": "",
        "rep_candidate": "",
        "margin": 0,
        "margin_pct": 0.0,
        "winner": "TIE",
        "color": "#d9d9d9"
      },
      "20": {
        "dem_votes": 0,
        "rep_votes": 0,
        "other_votes": 36150,
        "total_votes": 36150,
        "dem_candidate": "",
        "rep_candidate": "",
        "margin": 0,
        "margin_pct": 0.0,
        "winner": "TIE",
        "color": "#d9d9d9"
      },
      "21": {
        "dem_votes": 0,
        "rep_votes": 0,
        "other_votes": 45973,
        "total_votes": 45973,
        "dem_candidate": "",
        "rep_candidate": "",
        "margin": 0,
        "margin_pct": 0.0,
        "winner": "TIE",
        "color": "#d9d9d9"
      },
      "22": {
        "dem_votes": 0,
        "rep_votes": 0,
        "other_votes": 36074,
        "total_votes": 36074,
        "dem_candidate": "",
        "rep_candidate": "",
        "margin": 0,
        "margin_pct": 0.0,
        "winner": "TIE",
        "color": "#d9d9d9"
      },
      "23": {
        "dem_votes": 0,
        "rep_votes": 0,
        "other_votes": 34715,
        "total_votes": 34715,
        "dem_candidate": "",
        "rep_candidate": "",
        "margin": 0,
        "margin_pct": 0.0,
        "winner": "TIE",
        "color": "#d9d9d9"
      },
      "24": {
        "dem_votes": 0,
        "rep_votes": 0,
        "other_votes": 48411,
        "total_votes": 48411,
        "dem_candidate": "",
        "rep_candidate": "",
        "margin": 0,
        "margin_pct": 0.0,
        "winner": "TIE",
        "color": "#d9d9d9"
      },
      "25": {
        "dem_votes": 0,
        "rep_votes": 0,
        "other_votes": 30901,
        "total_votes": 30901,
        "dem_candidate": "",
        "rep_candidate": "",
        "margin": 0,
        "margin_pct": 0.0,
        "winner": "TIE",
        "color": "#d9d9d9"
      },
      "26": {
        "dem_votes": 0,
        "rep_votes": 0,
        "other_votes": 34894,
        "total_votes": 34894,
        "dem_candidate": "",
        "rep_candidate": "",
        "margin": 0,
        "margin_pct": 0.0,
        "winner": "TIE",
        "color": "#d9d9d9"
      },
      "27": {
        "dem_votes": 0,
        "rep_votes": 0,
        "other_votes": 43163,
        "total_votes": 43163,
        "dem_candidate": "",
        "rep_candidate": "",
        "margin": 0,
        "margin_pct": 0.0,
        "winner": "TIE",
        "color": "#d9d9d9"
      },
      "28": {
        "dem_votes": 0,
        "rep_votes": 0,
        "other_votes": 44261,
        "total_votes": 44261,
        "dem_candidate": "",
        "rep_candidate": "",
        "margin": 0,
        "margin_pct": 0.0,
        "winner": "TIE",
        "color": "#d9d9d9"
      },
      "29": {
        "dem_votes": 0,
        "rep_votes": 0,
        "other_votes": 35602,
        "total_votes": 35602,
        "dem_candidate": "",
        "rep_candidate": "",
        "margin": 0,
        "margin_pct": 0.0,
        "winner": "TIE",
        "color": "#d9d9d9"
      },
      "30": {
        "dem_votes": 0,
        "rep_votes": 0,
        "other_votes": 41899,
        "total_votes": 41899,
        "dem_candidate": "",
        "rep_candidate": "",
        "margin": 0,
        "margin_pct": 0.0,
        "winner": "TIE",
        "color": "#d9d9d9"
      },
      "31": {
        "dem_votes": 0,
        "rep_votes": 0,
        "other_votes": 25301,
        "total_votes": 25301,
        "dem_candidate": "",
        "rep_candidate": "",
        "margin": 0,
        "margin_pct": 0.0,
        "winner": "TIE",
        "color": "#d9d9d9"
      },
      "32": {
        "dem_votes": 0,
        "rep_votes": 0,
        "other_votes": 24946,
        "total_votes": 24946,
        "dem_candidate": "",
        "rep_candidate": "",
        "margin": 0,
        "margin_pct": 0.0,
        "winner": "TIE",
        "color": "#d9d9d9"
      },
      "33": {
        "dem_votes": 0,
        "rep_votes": 0,
        "other_votes": 32242,
        "total_votes": 32242,
        "dem_candidate": "",
        "rep_candidate": "",
        "margin": 0,
        "margin_pct": 0.0,
        "winner": "TIE",
        "color": "#d9d9d9"
      },
      "34": {
        "dem_votes": 0,
        "rep_votes": 0,
        "other_votes": 20394,
        "total_votes": 20394,
        "dem_candidate": "",
        "rep_candidate": "",
        "margin": 0,
        "margin_pct": 0.0,
        "winner": "TIE",
        "color": "#d9d9d9"
      },
      "35": {
        "dem_votes": 0,
        "rep_votes": 0,
        "other_votes": 14918,
        "total_votes": 14918,
        "dem_candidate": "",
        "rep_candidate": "",
        "margin": 0,
        "margin_pct": 0.0,
        "winner": "TIE",
        "color": "#d9d9d9"
      },
      "36": {
        "dem_votes": 0,
        "rep_votes": 0,
        "other_votes": 24002,
        "total_votes": 24002,
        "dem_candidate": "",
        "rep_candidate": "",
        "margin": 0,
        "margin_pct": 0.0,
        "winner": "TIE",
        "color": "#d9d9d9"
      },
      "37": {
        "dem_votes": 0,
        "rep_votes": 0,
        "other_votes": 31077,
        "total_votes": 31077,
        "dem_candidate": "",
        "rep_candidate": "",
        "margin": 0,
        "margin_pct": 0.0,
        "winner": "TIE",
        "color": "#d9d9d9"
      },
      "38": {
        "dem_votes": 0,
        "rep_votes": 0,
        "other_votes": 30768,
        "total_votes": 30768,
        "dem_candidate": "",
        "rep_candidate": "",
        "margin": 0,
        "margin_pct": 0.0,
        "winner": "TIE",
        "color": "#d9d9d9"
      },
      "39": {
        "dem_votes": 0,
        "rep_votes": 0,
        "other_votes": 27133,
        "total_votes": 27133,
        "dem_candidate": "",
        "rep_candidate": "",
        "margin": 0,
        "margin_pct": 0.0,
        "winner": "TIE",
        "color": "#d9d9d9"
      },
      "40": {
        "dem_votes": 0,
        "rep_votes": 0,
        "other_votes": 39227,
        "total_votes": 39227,
        "dem_candidate": "",
        "rep_candidate": "",
        "margin": 0,
        "margin_pct": 0.0,
        "winner": "TIE",
        "color": "#d9d9d9"
      },
      "41": {
        "dem_votes": 0,
        "rep_votes": 0,
        "other_votes": 45743,
        "total_votes": 45743,
        "dem_candidate": "",
        "rep_candidate": "",
        "margin": 0,
        "margin_pct": 0.0,
        "winner": "TIE",
        "color": "#d9d9d9"
      },
      "42": {
        "dem_votes": 0,
        "rep_votes": 0,
        "other_votes": 39327,
        "total_votes": 39327,
        "dem_candidate": "",
        "rep_candidate": "",
        "margin": 0,
        "margin_pct": 0.0,
        "winner": "TIE",
        "color": "#d9d9d9"
      },
      "43": {
        "dem_votes": 0,
        "rep_votes": 0,
        "other_votes": 39762,
        "total_votes": 39762,
        "dem_candidate": "",
        "rep_candidate": "",
        "margin": 0,
        "margin_pct": 0.0,
        "winner": "TIE",
        "color": "#d9d9d9"
      },
      "44": {
        "dem_votes": 0,
        "rep_votes": 0,
        "other_votes": 27974,
        "total_votes": 27974,
        "dem_candidate": "",
        "rep_candidate": "",
        "margin": 0,
        "margin_pct": 0.0,
        "winner": "TIE",
        "color": "#d9d9d9"
      },
      "45": {
        "dem_votes": 0,
        "rep_votes": 0,
        "other_votes": 29575,
        "total_votes": 29575,
        "dem_candidate": "",
        "rep_candidate": "",
        "margin": 0,
        "margin_pct": 0.0,
        "winner": "TIE",
        "color": "#d9d9d9"
      },
      "46": {
        "dem_votes": 0,
        "rep_votes": 0,
        "other_votes": 33843,
        "total_votes": 33843,
        "dem_candidate": "",
        "rep_candidate": "",
        "margin": 0,
        "margin_pct": 0.0,
        "winner": "TIE",
        "color": "#d9d9d9"
      },
      "47": {
        "dem_votes": 0,
        "rep_votes": 0,
        "other_votes": 40269,
        "total_votes": 40269,
        "dem_candidate": "",
        "rep_candidate": "",
        "margin": 0,
        "margin_pct": 0.0,
        "winner": "TIE",
        "color": "#d9d9d9"
      },
      "48": {
        "dem_votes": 0,
        "rep_votes": 0,
        "other_votes": 33722,
        "total_votes": 33722,
        "dem_candidate": "",
        "rep_candidate": "",
        "margin": 0,
        "margin_pct": 0.0,
        "winner": "TIE",
        "color": "#d9d9d9"
      },
      "49": {
        "dem_votes": 0,
        "rep_votes": 0,
        "other_votes": 24500,
        "total_votes": 24500,
        "dem_candidate": "",
        "rep_candidate": "",
        "margin": 0,
        "margin_pct": 0.0,
        "winner": "TIE",
        "color": "#d9d9d9"
      },
      "50": {
        "dem_votes": 0,
        "rep_votes": 0,
        "other_votes": 33101,
        "total_votes": 33101,
        "dem_candidate": "",
        "rep_candidate": "",
        "margin": 0,
        "margin_pct": 0.0,
        "winner": "TIE",
        "color": "#d9d9d9"
      },
      "51": {
        "dem_votes": 0,
        "rep_votes": 0,
        "other_votes": 30717,
        "total_votes": 30717,
        "dem_candidate": "",
        "rep_candidate": "",
        "margin": 0,
        "margin_pct": 0.0,
        "winner": "TIE",
        "color": "#d9d9d9"
      },
      "52": {
        "dem_votes": 0,
        "rep_votes": 0,
        "other_votes": 45112,
        "total_votes": 45112,
        "dem_candidate": "",
        "rep_candidate": "",
        "margin": 0,
        "margin_pct": 0.0,
        "winner": "TIE",
        "color": "#d9d9d9"
      },
      "53": {
        "dem_votes": 0,
        "rep_votes": 0,
        "other_votes": 32366,
        "total_votes": 32366,
        "dem_candidate": "",
        "rep_candidate": "",
        "margin": 0,
        "margin_pct": 0.0,
        "winner": "TIE",
        "color": "#d9d9d9"
      },
      "54": {
        "dem_votes": 0,
        "rep_votes": 0,
        "other_votes": 37704,
        "total_votes": 37704,
        "dem_candidate": "",
        "rep_candidate": "",
        "margin": 0,
        "margin_pct": 0.0,
        "winner": "TIE",
        "color": "#d9d9d9"
      },
      "55": {
        "dem_votes": 0,
        "rep_votes": 0,
        "other_votes": 27927,
        "total_votes": 27927,
        "dem_candidate": "",
        "rep_candidate": "",
        "margin": 0,
        "margin_pct": 0.0,
        "winner": "TIE",
        "color": "#d9d9d9"
      },
      "56": {
        "dem_votes": 0,
        "rep_votes": 0,
        "other_votes": 28398,
        "total_votes": 28398,
        "dem_candidate": "",
        "rep_candidate": "",
        "margin": 0,
        "margin_pct": 0.0,
        "winner": "TIE",
        "color": "#d9d9d9"
      },
      "57": {
        "dem_votes": 0,
        "rep_votes": 0,
        "other_votes": 34208,
        "total_votes": 34208,
        "dem_candidate": "",
        "rep_candidate": "",
        "margin": 0,
        "margin_pct": 0.0,
        "winner": "TIE",
        "color": "#d9d9d9"
      },
      "58": {
        "dem_votes": 0,
        "rep_votes": 0,
        "other_votes": 25330,
        "total_votes": 25330,
        "dem_candidate": "",
        "rep_candidate": "",
        "margin": 0,
        "margin_pct": 0.0,
        "winner": "TIE",
        "color": "#d9d9d9"
      },
      "59": {
        "dem_votes": 0,
        "rep_votes": 0,
        "other_votes": 40824,
        "total_votes": 40824,
        "dem_candidate": "",
        "rep_candidate": "",
        "margin": 0,
        "margin_pct": 0.0,
        "winner": "TIE",
        "color": "#d9d9d9"
      },
      "60": {
        "dem_votes": 0,
        "rep_votes": 0,
        "other_votes": 31339,
        "total_votes": 31339,
        "dem_candidate": "",
        "rep_candidate": "",
        "margin": 0,
        "margin_pct": 0.0,
        "winner": "TIE",
        "color": "#d9d9d9"
      },
      "61": {
        "dem_votes": 0,
        "rep_votes": 0,
        "other_votes": 42828,
        "total_votes": 42828,
        "dem_candidate": "",
        "rep_candidate": "",
        "margin": 0,
        "margin_pct": 0.0,
        "winner": "TIE",
        "color": "#d9d9d9"
      },
      "62": {
        "dem_votes": 0,
        "rep_votes": 0,
        "other_votes": 41043,
        "total_votes": 41043,
        "dem_candidate": "",
        "rep_candidate": "",
        "margin": 0,
        "margin_pct": 0.0,
        "winner": "TIE",
        "color": "#d9d9d9"
      },
      "63": {
        "dem_votes": 0,
        "rep_votes": 0,
        "other_votes": 30555,
        "total_votes": 30555,
        "dem_candidate": "",
        "rep_candidate": "",
        "margin": 0,
        "margin_pct": 0.0,
        "winner": "TIE",
        "color": "#d9d9d9"
      },
      "64": {
        "dem_votes": 0,
        "rep_votes": 0,
        "other_votes": 24074,
        "total_votes": 24074,
        "dem_candidate": "",
        "rep_candidate": "",
        "margin": 0,
        "margin_pct": 0.0,
        "winner": "TIE",
        "color": "#d9d9d9"
      },
      "65": {
        "dem_votes": 0,
        "rep_votes": 0,
        "other_votes": 37016,
        "total_votes": 37016,
        "dem_candidate": "",
        "rep_candidate": "",
        "margin": 0,
        "margin_pct": 0.0,
        "winner": "TIE",
        "color": "#d9d9d9"
      },
      "66": {
        "dem_votes": 0,
        "rep_votes": 0,
        "other_votes": 32512,
        "total_votes": 32512,
        "dem_candidate": "",
        "rep_candidate": "",
        "margin": 0,
        "margin_pct": 0.0,
        "winner": "TIE",
        "color": "#d9d9d9"
      },
      "67": {
        "dem_votes": 0,
        "rep_votes": 0,
        "other_votes": 43244,
        "total_votes": 43244,
        "dem_candidate": "",
        "rep_candidate": "",
        "margin": 0,
        "margin_pct": 0.0,
        "winner": "TIE",
        "color": "#d9d9d9"
      },
      "68": {
        "dem_votes": 0,
        "rep_votes": 0,
        "other_votes": 41019,
        "total_votes": 41019,
        "dem_candidate": "",
        "rep_candidate": "",
        "margin": 0,
        "margin_pct": 0.0,
        "winner": "TIE",
        "color": "#d9d9d9"
      },
      "69": {
        "dem_votes": 0,
        "rep_votes": 0,
        "other_votes": 35461,
        "total_votes": 35461,
        "dem_candidate": "",
        "rep_candidate": "",
        "margin": 0,
        "margin_pct": 0.0,
        "winner": "TIE",
        "color": "#d9d9d9"
      },
      "70": {
        "dem_votes": 0,
        "rep_votes": 0,
        "other_votes": 31152,
        "total_votes": 31152,
        "dem_candidate": "",
        "rep_candidate": "",
        "margin": 0,
        "margin_pct": 0.0,
        "winner": "TIE",
        "color": "#d9d9d9"
      },
      "71": {
        "dem_votes": 0,
        "rep_votes": 0,
        "other_votes": 32503,
        "total_votes": 32503,
        "dem_candidate": "",
        "rep_candidate": "",
        "margin": 0,
        "margin_pct": 0.0,
        "winner": "TIE",
        "color": "#d9d9d9"
      },
      "72": {
        "dem_votes": 0,
        "rep_votes": 0,
        "other_votes": 33769,
        "total_votes": 33769,
        "dem_candidate": "",
        "rep_candidate": "",
        "margin": 0,
        "margin_pct": 0.0,
        "winner": "TIE",
        "color": "#d9d9d9"
      },
      "73": {
        "dem_votes": 0,
        "rep_votes": 0,
        "other_votes": 39264,
        "total_votes": 39264,
        "dem_candidate": "",
        "rep_candidate": "",
        "margin": 0,
        "margin_pct": 0.0,
        "winner": "TIE",
        "color": "#d9d9d9"
      },
      "74": {
        "dem_votes": 0,
        "rep_votes": 0,
        "other_votes": 30670,
        "total_votes": 30670,
        "dem_candidate": "",
        "rep_candidate": "",
        "margin": 0,
        "margin_pct": 0.0,
        "winner": "TIE",
        "color": "#d9d9d9"
      },
      "75": {
        "dem_votes": 0,
        "rep_votes": 0,
        "other_votes": 33799,
        "total_votes": 33799,
        "dem_candidate": "",
        "rep_candidate": "",
        "margin": 0,
        "margin_pct": 0.0,
        "winner": "TIE",
        "color": "#d9d9d9"
      },
      "76": {
        "dem_votes": 0,
        "rep_votes": 0,
        "other_votes": 36762,
        "total_votes": 36762,
        "dem_candidate": "",
        "rep_candidate": "",
        "margin": 0,
        "margin_pct": 0.0,
        "winner": "TIE",
        "color": "#d9d9d9"
      },
      "77": {
        "dem_votes": 0,
        "rep_votes": 0,
        "other_votes": 34633,
        "total_votes": 34633,
        "dem_candidate": "",
        "rep_candidate": "",
        "margin": 0,
        "margin_pct": 0.0,
        "winner": "TIE",
        "color": "#d9d9d9"
      },
      "78": {
        "dem_votes": 0,
        "rep_votes": 0,
        "other_votes": 34606,
        "total_votes": 34606,
        "dem_candidate": "",
        "rep_candidate": "",
        "margin": 0,
        "margin_pct": 0.0,
        "winner": "TIE",
        "color": "#d9d9d9"
      },
      "79": {
        "dem_votes": 0,
        "rep_votes": 0,
        "other_votes": 28949,
        "total_votes": 28949,
        "dem_candidate": "",
        "rep_candidate": "",
        "margin": 0,
        "margin_pct": 0.0,
        "winner": "TIE",
        "color": "#d9d9d9"
      },
      "80": {
        "dem_votes": 0,
        "rep_votes": 0,
        "other_votes": 43251,
        "total_votes": 43251,
        "dem_candidate": "",
        "rep_candidate": "",
        "margin": 0,
        "margin_pct": 0.0,
        "winner": "TIE",
        "color": "#d9d9d9"
      },
      "81": {
        "dem_votes": 0,
        "rep_votes": 0,
        "other_votes": 35916,
        "total_votes": 35916,
        "dem_candidate": "",
        "rep_candidate": "",
        "margin": 0,
        "margin_pct": 0.0,
        "winner": "TIE",
        "color": "#d9d9d9"
      },
      "82": {
        "dem_votes": 0,
        "rep_votes": 0,
        "other_votes": 34278,
        "total_votes": 34278,
        "dem_candidate": "",
        "rep_candidate": "",
        "margin": 0,
        "margin_pct": 0.0,
        "winner": "TIE",
        "color": "#d9d9d9"
      },
      "83": {
        "dem_votes": 0,
        "rep_votes": 0,
        "other_votes": 29503,
        "total_votes": 29503,
        "dem_candidate": "",
        "rep_candidate": "",
        "margin": 0,
        "margin_pct": 0.0,
        "winner": "TIE",
        "color": "#d9d9d9"
      },
      "84": {
        "dem_votes": 0,
        "rep_votes": 0,
        "other_votes": 42397,
        "total_votes": 42397,
        "dem_candidate": "",
        "rep_candidate": "",
        "margin": 0,
        "margin_pct": 0.0,
        "winner": "TIE",
        "color": "#d9d9d9"
      },
      "85": {
        "dem_votes": 0,
        "rep_votes": 0,
        "other_votes": 34634,
        "total_votes": 34634,
        "dem_candidate": "",
        "rep_candidate": "",
        "margin": 0,
        "margin_pct": 0.0,
        "winner": "TIE",
        "color": "#d9d9d9"
      },
      "86": {
        "dem_votes": 0,
        "rep_votes": 0,
        "other_votes": 26278,
        "total_votes": 26278,
        "dem_candidate": "",
        "rep_candidate": "",
        "margin": 0,
        "margin_pct": 0.0,
        "winner": "TIE",
        "color": "#d9d9d9"
      },
      "87": {
        "dem_votes": 0,
        "rep_votes": 0,
        "other_votes": 32270,
        "total_votes": 32270,
        "dem_candidate": "",
        "rep_candidate": "",
        "margin": 0,
        "margin_pct": 0.0,
        "winner": "TIE",
        "color": "#d9d9d9"
      },
      "88": {
        "dem_votes": 0,
        "rep_votes": 0,
        "other_votes": 34862,
        "total_votes": 34862,
        "dem_candidate": "",
        "rep_candidate": "",
        "margin": 0,
        "margin_pct": 0.0,
        "winner": "TIE",
        "color": "#d9d9d9"
      },
      "89": {
        "dem_votes": 0,
        "rep_votes": 0,
        "other_votes": 41153,
        "total_votes": 41153,
        "dem_candidate": "",
        "rep_candidate": "",
        "margin": 0,
        "margin_pct": 0.0,
        "winner": "TIE",
        "color": "#d9d9d9"
      },
      "90": {
        "dem_votes": 0,
        "rep_votes": 0,
        "other_votes": 32689,
        "total_votes": 32689,
        "dem_candidate": "",
        "rep_candidate": "",
        "margin": 0,
        "margin_pct": 0.0,
        "winner": "TIE",
        "color": "#d9d9d9"
      },
      "91": {
        "dem_votes": 0,
        "rep_votes": 0,
        "other_votes": 33613,
        "total_votes": 33613,
        "dem_candidate": "",
        "rep_candidate": "",
        "margin": 0,
        "margin_pct": 0.0,
        "winner": "TIE",
        "color": "#d9d9d9"
      },
      "92": {
        "dem_votes": 0,
        "rep_votes": 0,
        "other_votes": 30482,
        "total_votes": 30482,
        "dem_candidate": "",
        "rep_candidate": "",
        "margin": 0,
        "margin_pct": 0.0,
        "winner": "TIE",
        "color": "#d9d9d9"
      },
      "93": {
        "dem_votes": 0,
        "rep_votes": 0,
        "other_votes": 32811,
        "total_votes": 32811,
        "dem_candidate": "",
        "rep_candidate": "",
        "margin": 0,
        "margin_pct": 0.0,
        "winner": "TIE",
        "color": "#d9d9d9"
      },
      "94": {
        "dem_votes": 0,
        "rep_votes": 0,
        "other_votes": 30703,
        "total_votes": 30703,
        "dem_candidate": "",
        "rep_candidate": "",
        "margin": 0,
        "margin_pct": 0.0,
        "winner": "TIE",
        "color": "#d9d9d9"
      },
      "95": {
        "dem_votes": 0,
        "rep_votes": 0,
        "other_votes": 46933,
        "total_votes": 46933,
        "dem_candidate": "",
        "rep_candidate": "",
        "margin": 0,
        "margin_pct": 0.0,
        "winner": "TIE",
        "color": "#d9d9d9"
      },
      "96": {
        "dem_votes": 0,
        "rep_votes": 0,
        "other_votes": 37323,
        "total_votes": 37323,
        "dem_candidate": "",
        "rep_candidate": "",
        "margin": 0,
        "margin_pct": 0.0,
        "winner": "TIE",
        "color": "#d9d9d9"
      },
      "97": {
        "dem_votes": 0,
        "rep_votes": 0,
        "other_votes": 31210,
        "total_votes": 31210,
        "dem_candidate": "",
        "rep_candidate": "",
        "margin": 0,
        "margin_pct": 0.0,
        "winner": "TIE",
        "color": "#d9d9d9"
      },
      "98": {
        "dem_votes": 0,
        "rep_votes": 0,
        "other_votes": 32442,
        "total_votes": 32442,
        "dem_candidate": "",
        "rep_candidate": "",
        "margin": 0,
        "margin_pct": 0.0,
        "winner": "TIE",
        "color": "#d9d9d9"
      },
      "99": {
        "dem_votes": 0,
        "rep_votes": 0,
        "other_votes": 28022,
        "total_votes": 28022,
        "dem_candidate": "",
        "rep_candidate": "",
        "margin": 0,
        "margin_pct": 0.0,
        "winner": "TIE",
        "color": "#d9d9d9"
      },
      "ZZZ": {
        "dem_votes": 0,
        "rep_votes": 0,
        "other_votes": 8139,
        "total_votes": 8139,
        "dem_candidate": "",
        "rep_candidate": "",
        "margin": 0,
        "margin_pct": 0.0,
        "winner": "TIE",
        "color": "#d9d9d9"
      }
    }
  }
}
