{
  "scope": "state_house",
  "contest_type": "secretary_of_state",
  "year": 2018,
  "general": {
    "results": {
      "1": {
        "dem_votes": 34345,
        "rep_votes": 7477,
        "other_votes": 794,
        "total_votes": 42616,
        "dem_candidate": "Kathleen Clyde",
        "rep_candidate": "Frank LaRose",
        "margin": -26868,
        "margin_pct": -63.04674300732119,
        "winner": "DEM",
        "color": "#2171b5"
      },
      "2": {
        "dem_votes": 26883,
        "rep_votes": 8614,
        "other_votes": 706,
        "total_votes": 36203,
        "dem_candidate": "Kathleen Clyde",
        "rep_candidate": "Frank LaRose",
        "margin": -18269,
        "margin_pct": -50.462668839598926,
        "winner": "DEM",
        "color": "#2171b5"
      },
      "3": {
        "dem_votes": 30725,
        "rep_votes": 5579,
        "other_votes": 750,
        "total_votes": 37054,
        "dem_candidate": "Kathleen Clyde",
        "rep_candidate": "Frank LaRose",
        "margin": -25146,
        "margin_pct": -67.86311869163923,
        "winner": "DEM",
        "color": "#2171b5"
      },
      "4": {
        "dem_votes": 27589,
        "rep_votes": 23690,
        "other_votes": 1093,
        "total_votes": 52372,
        "dem_candidate": "Kathleen Clyde",
        "rep_candidate": "Frank LaRose",
        "margin": -3899,
        "margin_pct": -7.444817841594745,
        "winner": "DEM",
        "color": "#6baed6"
      },
      "5": {
        "dem_votes": 20445,
        "rep_votes": 18435,
        "other_votes": 872,
        "total_votes": 39752,
        "dem_candidate": "Kathleen Clyde",
        "rep_candidate": "Frank LaRose",
        "margin": -2010,
        "margin_pct": -5.0563493660696315,
        "winner": "DEM",
        "color": "#6baed6"
      },
      "6": {
        "dem_votes": 18163,
        "rep_votes": 12575,
        "other_votes": 786,
        "total_votes": 31524,
        "dem_candidate": "Kathleen Clyde",
        "rep_candidate": "Frank LaRose",
        "margin": -5588,
        "margin_pct": -17.726176881106458,
        "winner": "DEM",
        "color": "#2171b5"
      },
      "7": {
        "dem_votes": 35343,
        "rep_votes": 17164,
        "other_votes": 1021,
        "total_votes": 53528,
        "dem_candidate": "Kathleen Clyde",
        "rep_candidate": "Frank LaRose",
        "margin": -18179,
        "margin_pct": -33.96166492303094,
        "winner": "DEM",
        "color": "#2171b5"
      },
      "8": {
        "dem_votes": 33745,
        "rep_votes": 19404,
        "other_votes": 1198,
        "total_votes": 54347,
        "dem_candidate": "Kathleen Clyde",
        "rep_candidate": "Frank LaRose",
        "margin": -14341,
        "margin_pct": -26.387841095184644,
        "winner": "DEM",
        "color": "#2171b5"
      },
      "9": {
        "dem_votes": 25926,
        "rep_votes": 11789,
        "other_votes": 827,
        "total_votes": 38542,
        "dem_candidate": "Kathleen Clyde",
        "rep_candidate": "Frank LaRose",
        "margin": -14137,
        "margin_pct": -36.67946655596492,
        "winner": "DEM",
        "color": "#2171b5"
      },
      "10": {
        "dem_votes": 18195,
        "rep_votes": 16725,
        "other_votes": 793,
        "total_votes": 35713,
        "dem_candidate": "Kathleen Clyde",
        "rep_candidate": "Frank LaRose",
        "margin": -1470,
        "margin_pct": -4.116148181334528,
        "winner": "DEM",
        "color": "#c6dbef"
      },
      "11": {
        "dem_votes": 27508,
        "rep_votes": 24106,
        "other_votes": 1076,
        "total_votes": 52690,
        "dem_candidate": "Kathleen Clyde",
        "rep_candidate": "Frank LaRose",
        "margin": -3402,
        "margin_pct": -6.456633137217688,
        "winner": "DEM",
        "color": "#6baed6"
      },
      "12": {
        "dem_votes": 11884,
        "rep_votes": 24038,
        "other_votes": 875,
        "total_votes": 36797,
        "dem_candidate": "Kathleen Clyde",
        "rep_candidate": "Frank LaRose",
        "margin": 12154,
        "margin_pct": 33.02986656520912,
        "winner": "REP",
        "color": "#cb181d"
      },
      "13": {
        "dem_votes": 30051,
        "rep_votes": 9632,
        "other_votes": 1151,
        "total_votes": 40834,
        "dem_candidate": "Kathleen Clyde",
        "rep_candidate": "Frank LaRose",
        "margin": -20419,
        "margin_pct": -50.004897879218305,
        "winner": "DEM",
        "color": "#2171b5"
      },
      "14": {
        "dem_votes": 22432,
        "rep_votes": 16872,
        "other_votes": 1159,
        "total_votes": 40463,
        "dem_candidate": "Kathleen Clyde",
        "rep_candidate": "Frank LaRose",
        "margin": -5560,
        "margin_pct": -13.74094852087092,
        "winner": "DEM",
        "color": "#6baed6"
      },
      "15": {
        "dem_votes": 22791,
        "rep_votes": 20050,
        "other_votes": 1067,
        "total_votes": 43908,
        "dem_candidate": "Kathleen Clyde",
        "rep_candidate": "Frank LaRose",
        "margin": -2741,
        "margin_pct": -6.242598159788649,
        "winner": "DEM",
        "color": "#6baed6"
      },
      "16": {
        "dem_votes": 28691,
        "rep_votes": 23650,
        "other_votes": 1186,
        "total_votes": 53527,
        "dem_candidate": "Kathleen Clyde",
        "rep_candidate": "Frank LaRose",
        "margin": -5041,
        "margin_pct": -9.417677060175238,
        "winner": "DEM",
        "color": "#6baed6"
      },
      "17": {
        "dem_votes": 27365,
        "rep_votes": 24357,
        "other_votes": 1215,
        "total_votes": 52937,
        "dem_candidate": "Kathleen Clyde",
        "rep_candidate": "Frank LaRose",
        "margin": -3008,
        "margin_pct": -5.682226042276668,
        "winner": "DEM",
        "color": "#6baed6"
      },
      "18": {
        "dem_votes": 36217,
        "rep_votes": 3929,
        "other_votes": 594,
        "total_votes": 40740,
        "dem_candidate": "Kathleen Clyde",
        "rep_candidate": "Frank LaRose",
        "margin": -32288,
        "margin_pct": -79.25380461462936,
        "winner": "DEM",
        "color": "#2171b5"
      },
      "19": {
        "dem_votes": 33923,
        "rep_votes": 20374,
        "other_votes": 951,
        "total_votes": 55248,
        "dem_candidate": "Kathleen Clyde",
        "rep_candidate": "Frank LaRose",
        "margin": -13549,
        "margin_pct": -24.523964668404286,
        "winner": "DEM",
        "color": "#2171b5"
      },
      "20": {
        "dem_votes": 29889,
        "rep_votes": 3431,
        "other_votes": 672,
        "total_votes": 33992,
        "dem_candidate": "Kathleen Clyde",
        "rep_candidate": "Frank LaRose",
        "margin": -26458,
        "margin_pct": -77.83596140268298,
        "winner": "DEM",
        "color": "#2171b5"
      },
      "21": {
        "dem_votes": 38895,
        "rep_votes": 11623,
        "other_votes": 900,
        "total_votes": 51418,
        "dem_candidate": "Kathleen Clyde",
        "rep_candidate": "Frank LaRose",
        "margin": -27272,
        "margin_pct": -53.03979151269983,
        "winner": "DEM",
        "color": "#2171b5"
      },
      "22": {
        "dem_votes": 47670,
        "rep_votes": 6485,
        "other_votes": 796,
        "total_votes": 54951,
        "dem_candidate": "Kathleen Clyde",
        "rep_candidate": "Frank LaRose",
        "margin": -41185,
        "margin_pct": -74.94859056250114,
        "winner": "DEM",
        "color": "#2171b5"
      },
      "23": {
        "dem_votes": 26148,
        "rep_votes": 24232,
        "other_votes": 1155,
        "total_votes": 51535,
        "dem_candidate": "Kathleen Clyde",
        "rep_candidate": "Frank LaRose",
        "margin": -1916,
        "margin_pct": -3.71786164742408,
        "winner": "DEM",
        "color": "#c6dbef"
      },
      "24": {
        "dem_votes": 26140,
        "rep_votes": 10398,
        "other_votes": 1030,
        "total_votes": 37568,
        "dem_candidate": "Kathleen Clyde",
        "rep_candidate": "Frank LaRose",
        "margin": -15742,
        "margin_pct": -41.902683134582624,
        "winner": "DEM",
        "color": "#2171b5"
      },
      "25": {
        "dem_votes": 28462,
        "rep_votes": 8155,
        "other_votes": 879,
        "total_votes": 37496,
        "dem_candidate": "Kathleen Clyde",
        "rep_candidate": "Frank LaRose",
        "margin": -20307,
        "margin_pct": -54.15777682952848,
        "winner": "DEM",
        "color": "#2171b5"
      },
      "26": {
        "dem_votes": 38778,
        "rep_votes": 14598,
        "other_votes": 1225,
        "total_votes": 54601,
        "dem_candidate": "Kathleen Clyde",
        "rep_candidate": "Frank LaRose",
        "margin": -24180,
        "margin_pct": -44.28490320690097,
        "winner": "DEM",
        "color": "#2171b5"
      },
      "27": {
        "dem_votes": 29952,
        "rep_votes": 27304,
        "other_votes": 1331,
        "total_votes": 58587,
        "dem_candidate": "Kathleen Clyde",
        "rep_candidate": "Frank LaRose",
        "margin": -2648,
        "margin_pct": -4.519774011299435,
        "winner": "DEM",
        "color": "#c6dbef"
      },
      "28": {
        "dem_votes": 27434,
        "rep_votes": 24652,
        "other_votes": 1228,
        "total_votes": 53314,
        "dem_candidate": "Kathleen Clyde",
        "rep_candidate": "Frank LaRose",
        "margin": -2782,
        "margin_pct": -5.2181415763214165,
        "winner": "DEM",
        "color": "#6baed6"
      },
      "29": {
        "dem_votes": 17621,
        "rep_votes": 24189,
        "other_votes": 1056,
        "total_votes": 42866,
        "dem_candidate": "Kathleen Clyde",
        "rep_candidate": "Frank LaRose",
        "margin": 6568,
        "margin_pct": 15.322166752204543,
        "winner": "REP",
        "color": "#cb181d"
      },
      "30": {
        "dem_votes": 14893,
        "rep_votes": 35020,
        "other_votes": 1238,
        "total_votes": 51151,
        "dem_candidate": "Kathleen Clyde",
        "rep_candidate": "Frank LaRose",
        "margin": 20127,
        "margin_pct": 39.348204336181105,
        "winner": "REP",
        "color": "#cb181d"
      },
      "31": {
        "dem_votes": 27381,
        "rep_votes": 27488,
        "other_votes": 1078,
        "total_votes": 55947,
        "dem_candidate": "Kathleen Clyde",
        "rep_candidate": "Frank LaRose",
        "margin": 107,
        "margin_pct": 0.1912524353405902,
        "winner": "REP",
        "color": "#fcbba1"
      },
      "32": {
        "dem_votes": 20649,
        "rep_votes": 19218,
        "other_votes": 999,
        "total_votes": 40866,
        "dem_candidate": "Kathleen Clyde",
        "rep_candidate": "Frank LaRose",
        "margin": -1431,
        "margin_pct": -3.5016884451622374,
        "winner": "DEM",
        "color": "#c6dbef"
      },
      "33": {
        "dem_votes": 29648,
        "rep_votes": 9226,
        "other_votes": 821,
        "total_votes": 39695,
        "dem_candidate": "Kathleen Clyde",
        "rep_candidate": "Frank LaRose",
        "margin": -20422,
        "margin_pct": -51.44728555233657,
        "winner": "DEM",
        "color": "#2171b5"
      },
      "34": {
        "dem_votes": 26522,
        "rep_votes": 25139,
        "other_votes": 1128,
        "total_votes": 52789,
        "dem_candidate": "Kathleen Clyde",
        "rep_candidate": "Frank LaRose",
        "margin": -1383,
        "margin_pct": -2.619863986815435,
        "winner": "DEM",
        "color": "#c6dbef"
      },
      "35": {
        "dem_votes": 21657,
        "rep_votes": 26622,
        "other_votes": 1194,
        "total_votes": 49473,
        "dem_candidate": "Kathleen Clyde",
        "rep_candidate": "Frank LaRose",
        "margin": 4965,
        "margin_pct": 10.035777090534232,
        "winner": "REP",
        "color": "#fb6a4a"
      },
      "36": {
        "dem_votes": 22733,
        "rep_votes": 20862,
        "other_votes": 1261,
        "total_votes": 44856,
        "dem_candidate": "Kathleen Clyde",
        "rep_candidate": "Frank LaRose",
        "margin": -1871,
        "margin_pct": -4.171125378990547,
        "winner": "DEM",
        "color": "#c6dbef"
      },
      "37": {
        "dem_votes": 20380,
        "rep_votes": 32028,
        "other_votes": 1204,
        "total_votes": 53612,
        "dem_candidate": "Kathleen Clyde",
        "rep_candidate": "Frank LaRose",
        "margin": 11648,
        "margin_pct": 21.72647914645975,
        "winner": "REP",
        "color": "#cb181d"
      },
      "38": {
        "dem_votes": 23622,
        "rep_votes": 9915,
        "other_votes": 824,
        "total_votes": 34361,
        "dem_candidate": "Kathleen Clyde",
        "rep_candidate": "Frank LaRose",
        "margin": -13707,
        "margin_pct": -39.89115567067314,
        "winner": "DEM",
        "color": "#2171b5"
      },
      "39": {
        "dem_votes": 25534,
        "rep_votes": 22847,
        "other_votes": 1021,
        "total_votes": 49402,
        "dem_candidate": "Kathleen Clyde",
        "rep_candidate": "Frank LaRose",
        "margin": -2687,
        "margin_pct": -5.439051050564755,
        "winner": "DEM",
        "color": "#6baed6"
      },
      "40": {
        "dem_votes": 13478,
        "rep_votes": 28320,
        "other_votes": 1133,
        "total_votes": 42931,
        "dem_candidate": "Kathleen Clyde",
        "rep_candidate": "Frank LaRose",
        "margin": 14842,
        "margin_pct": 34.57175467610817,
        "winner": "REP",
        "color": "#cb181d"
      },
      "41": {
        "dem_votes": 22699,
        "rep_votes": 20407,
        "other_votes": 1330,
        "total_votes": 44436,
        "dem_candidate": "Kathleen Clyde",
        "rep_candidate": "Frank LaRose",
        "margin": -2292,
        "margin_pct": -5.157980016203078,
        "winner": "DEM",
        "color": "#6baed6"
      },
      "42": {
        "dem_votes": 22634,
        "rep_votes": 20686,
        "other_votes": 1286,
        "total_votes": 44606,
        "dem_candidate": "Kathleen Clyde",
        "rep_candidate": "Frank LaRose",
        "margin": -1948,
        "margin_pct": -4.367125498811819,
        "winner": "DEM",
        "color": "#c6dbef"
      },
      "43": {
        "dem_votes": 25979,
        "rep_votes": 12279,
        "other_votes": 1182,
        "total_votes": 39440,
        "dem_candidate": "Kathleen Clyde",
        "rep_candidate": "Frank LaRose",
        "margin": -13700,
        "margin_pct": -34.73630831643002,
        "winner": "DEM",
        "color": "#2171b5"
      },
      "44": {
        "dem_votes": 21678,
        "rep_votes": 8275,
        "other_votes": 766,
        "total_votes": 30719,
        "dem_candidate": "Kathleen Clyde",
        "rep_candidate": "Frank LaRose",
        "margin": -13403,
        "margin_pct": -43.63097757088447,
        "winner": "DEM",
        "color": "#2171b5"
      },
      "45": {
        "dem_votes": 18762,
        "rep_votes": 29487,
        "other_votes": 1120,
        "total_votes": 49369,
        "dem_candidate": "Kathleen Clyde",
        "rep_candidate": "Frank LaRose",
        "margin": 10725,
        "margin_pct": 21.724158885130347,
        "winner": "REP",
        "color": "#cb181d"
      },
      "46": {
        "dem_votes": 14432,
        "rep_votes": 25499,
        "other_votes": 970,
        "total_votes": 40901,
        "dem_candidate": "Kathleen Clyde",
        "rep_candidate": "Frank LaRose",
        "margin": 11067,
        "margin_pct": 27.058018141365736,
        "winner": "REP",
        "color": "#cb181d"
      },
      "47": {
        "dem_votes": 14765,
        "rep_votes": 21890,
        "other_votes": 894,
        "total_votes": 37549,
        "dem_candidate": "Kathleen Clyde",
        "rep_candidate": "Frank LaRose",
        "margin": 7125,
        "margin_pct": 18.975205731177926,
        "winner": "REP",
        "color": "#cb181d"
      },
      "48": {
        "dem_votes": 19482,
        "rep_votes": 29002,
        "other_votes": 1041,
        "total_votes": 49525,
        "dem_candidate": "Kathleen Clyde",
        "rep_candidate": "Frank LaRose",
        "margin": 9520,
        "margin_pct": 19.2226148409894,
        "winner": "REP",
        "color": "#cb181d"
      },
      "49": {
        "dem_votes": 18410,
        "rep_votes": 17095,
        "other_votes": 849,
        "total_votes": 36354,
        "dem_candidate": "Kathleen Clyde",
        "rep_candidate": "Frank LaRose",
        "margin": -1315,
        "margin_pct": -3.6172085602684714,
        "winner": "DEM",
        "color": "#c6dbef"
      },
      "50": {
        "dem_votes": 17096,
        "rep_votes": 22890,
        "other_votes": 1109,
        "total_votes": 41095,
        "dem_candidate": "Kathleen Clyde",
        "rep_candidate": "Frank LaRose",
        "margin": 5794,
        "margin_pct": 14.099038812507606,
        "winner": "REP",
        "color": "#fb6a4a"
      },
      "51": {
        "dem_votes": 14270,
        "rep_votes": 24467,
        "other_votes": 1028,
        "total_votes": 39765,
        "dem_candidate": "Kathleen Clyde",
        "rep_candidate": "Frank LaRose",
        "margin": 10197,
        "margin_pct": 25.643153526970952,
        "winner": "REP",
        "color": "#cb181d"
      },
      "52": {
        "dem_votes": 21413,
        "rep_votes": 18822,
        "other_votes": 1047,
        "total_votes": 41282,
        "dem_candidate": "Kathleen Clyde",
        "rep_candidate": "Frank LaRose",
        "margin": -2591,
        "margin_pct": -6.276343200426336,
        "winner": "DEM",
        "color": "#6baed6"
      },
      "53": {
        "dem_votes": 23802,
        "rep_votes": 17777,
        "other_votes": 1014,
        "total_votes": 42593,
        "dem_candidate": "Kathleen Clyde",
        "rep_candidate": "Frank LaRose",
        "margin": -6025,
        "margin_pct": -14.14551686896908,
        "winner": "DEM",
        "color": "#6baed6"
      },
      "54": {
        "dem_votes": 21005,
        "rep_votes": 24072,
        "other_votes": 1275,
        "total_votes": 46352,
        "dem_candidate": "Kathleen Clyde",
        "rep_candidate": "Frank LaRose",
        "margin": 3067,
        "margin_pct": 6.616758715913014,
        "winner": "REP",
        "color": "#fb6a4a"
      },
      "55": {
        "dem_votes": 13509,
        "rep_votes": 36130,
        "other_votes": 1242,
        "total_votes": 50881,
        "dem_candidate": "Kathleen Clyde",
        "rep_candidate": "Frank LaRose",
        "margin": 22621,
        "margin_pct": 44.45863878461508,
        "winner": "REP",
        "color": "#cb181d"
      },
      "56": {
        "dem_votes": 17317,
        "rep_votes": 28715,
        "other_votes": 1180,
        "total_votes": 47212,
        "dem_candidate": "Kathleen Clyde",
        "rep_candidate": "Frank LaRose",
        "margin": 11398,
        "margin_pct": 24.14216724561552,
        "winner": "REP",
        "color": "#cb181d"
      },
      "57": {
        "dem_votes": 21130,
        "rep_votes": 27554,
        "other_votes": 1101,
        "total_votes": 49785,
        "dem_candidate": "Kathleen Clyde",
        "rep_candidate": "Frank LaRose",
        "margin": 6424,
        "margin_pct": 12.90348498543738,
        "winner": "REP",
        "color": "#fb6a4a"
      },
      "58": {
        "dem_votes": 24909,
        "rep_votes": 24065,
        "other_votes": 1162,
        "total_votes": 50136,
        "dem_candidate": "Kathleen Clyde",
        "rep_candidate": "Frank LaRose",
        "margin": -844,
        "margin_pct": -1.6834210946226267,
        "winner": "DEM",
        "color": "#c6dbef"
      },
      "59": {
        "dem_votes": 22517,
        "rep_votes": 20581,
        "other_votes": 958,
        "total_votes": 44056,
        "dem_candidate": "Kathleen Clyde",
        "rep_candidate": "Frank LaRose",
        "margin": -1936,
        "margin_pct": -4.394407118213183,
        "winner": "DEM",
        "color": "#c6dbef"
      },
      "60": {
        "dem_votes": 19856,
        "rep_votes": 28740,
        "other_votes": 1133,
        "total_votes": 49729,
        "dem_candidate": "Kathleen Clyde",
        "rep_candidate": "Frank LaRose",
        "margin": 8884,
        "margin_pct": 17.864827364314586,
        "winner": "REP",
        "color": "#cb181d"
      },
      "61": {
        "dem_votes": 20430,
        "rep_votes": 30285,
        "other_votes": 1035,
        "total_votes": 51750,
        "dem_candidate": "Kathleen Clyde",
        "rep_candidate": "Frank LaRose",
        "margin": 9855,
        "margin_pct": 19.043478260869566,
        "winner": "REP",
        "color": "#cb181d"
      },
      "62": {
        "dem_votes": 16088,
        "rep_votes": 32150,
        "other_votes": 1447,
        "total_votes": 49685,
        "dem_candidate": "Kathleen Clyde",
        "rep_candidate": "Frank LaRose",
        "margin": 16062,
        "margin_pct": 32.32766428499547,
        "winner": "REP",
        "color": "#cb181d"
      },
      "63": {
        "dem_votes": 10426,
        "rep_votes": 27713,
        "other_votes": 1078,
        "total_votes": 39217,
        "dem_candidate": "Kathleen Clyde",
        "rep_candidate": "Frank LaRose",
        "margin": 17287,
        "margin_pct": 44.0803733074942,
        "winner": "REP",
        "color": "#cb181d"
      },
      "64": {
        "dem_votes": 24431,
        "rep_votes": 19055,
        "other_votes": 999,
        "total_votes": 44485,
        "dem_candidate": "Kathleen Clyde",
        "rep_candidate": "Frank LaRose",
        "margin": -5376,
        "margin_pct": -12.084972462627853,
        "winner": "DEM",
        "color": "#6baed6"
      },
      "65": {
        "dem_votes": 16108,
        "rep_votes": 24324,
        "other_votes": 1156,
        "total_votes": 41588,
        "dem_candidate": "Kathleen Clyde",
        "rep_candidate": "Frank LaRose",
        "margin": 8216,
        "margin_pct": 19.755698759257477,
        "winner": "REP",
        "color": "#cb181d"
      },
      "66": {
        "dem_votes": 18833,
        "rep_votes": 28701,
        "other_votes": 1141,
        "total_votes": 48675,
        "dem_candidate": "Kathleen Clyde",
        "rep_candidate": "Frank LaRose",
        "margin": 9868,
        "margin_pct": 20.273240883410377,
        "winner": "REP",
        "color": "#cb181d"
      },
      "67": {
        "dem_votes": 15618,
        "rep_votes": 26838,
        "other_votes": 1162,
        "total_votes": 43618,
        "dem_candidate": "Kathleen Clyde",
        "rep_candidate": "Frank LaRose",
        "margin": 11220,
        "margin_pct": 25.723325232702095,
        "winner": "REP",
        "color": "#cb181d"
      },
      "68": {
        "dem_votes": 16012,
        "rep_votes": 25775,
        "other_votes": 1000,
        "total_votes": 42787,
        "dem_candidate": "Kathleen Clyde",
        "rep_candidate": "Frank LaRose",
        "margin": 9763,
        "margin_pct": 22.81767826676327,
        "winner": "REP",
        "color": "#cb181d"
      },
      "69": {
        "dem_votes": 14942,
        "rep_votes": 29878,
        "other_votes": 1048,
        "total_votes": 45868,
        "dem_candidate": "Kathleen Clyde",
        "rep_candidate": "Frank LaRose",
        "margin": 14936,
        "margin_pct": 32.56300688933461,
        "winner": "REP",
        "color": "#cb181d"
      },
      "70": {
        "dem_votes": 17570,
        "rep_votes": 28927,
        "other_votes": 1237,
        "total_votes": 47734,
        "dem_candidate": "Kathleen Clyde",
        "rep_candidate": "Frank LaRose",
        "margin": 11357,
        "margin_pct": 23.79226547115264,
        "winner": "REP",
        "color": "#cb181d"
      },
      "71": {
        "dem_votes": 14120,
        "rep_votes": 28517,
        "other_votes": 1121,
        "total_votes": 43758,
        "dem_candidate": "Kathleen Clyde",
        "rep_candidate": "Frank LaRose",
        "margin": 14397,
        "margin_pct": 32.90141231317702,
        "winner": "REP",
        "color": "#cb181d"
      },
      "72": {
        "dem_votes": 23627,
        "rep_votes": 19836,
        "other_votes": 972,
        "total_votes": 44435,
        "dem_candidate": "Kathleen Clyde",
        "rep_candidate": "Frank LaRose",
        "margin": -3791,
        "margin_pct": -8.53156295712839,
        "winner": "DEM",
        "color": "#6baed6"
      },
      "73": {
        "dem_votes": 18429,
        "rep_votes": 25964,
        "other_votes": 991,
        "total_votes": 45384,
        "dem_candidate": "Kathleen Clyde",
        "rep_candidate": "Frank LaRose",
        "margin": 7535,
        "margin_pct": 16.602767495152477,
        "winner": "REP",
        "color": "#cb181d"
      },
      "74": {
        "dem_votes": 13207,
        "rep_votes": 17765,
        "other_votes": 853,
        "total_votes": 31825,
        "dem_candidate": "Kathleen Clyde",
        "rep_candidate": "Frank LaRose",
        "margin": 4558,
        "margin_pct": 14.32207384131972,
        "winner": "REP",
        "color": "#fb6a4a"
      },
      "75": {
        "dem_votes": 19149,
        "rep_votes": 21267,
        "other_votes": 1193,
        "total_votes": 41609,
        "dem_candidate": "Kathleen Clyde",
        "rep_candidate": "Frank LaRose",
        "margin": 2118,
        "margin_pct": 5.090244898940133,
        "winner": "REP",
        "color": "#fb6a4a"
      },
      "76": {
        "dem_votes": 14768,
        "rep_votes": 28162,
        "other_votes": 987,
        "total_votes": 43917,
        "dem_candidate": "Kathleen Clyde",
        "rep_candidate": "Frank LaRose",
        "margin": 13394,
        "margin_pct": 30.498440239542774,
        "winner": "REP",
        "color": "#cb181d"
      },
      "77": {
        "dem_votes": 13206,
        "rep_votes": 25513,
        "other_votes": 902,
        "total_votes": 39621,
        "dem_candidate": "Kathleen Clyde",
        "rep_candidate": "Frank LaRose",
        "margin": 12307,
        "margin_pct": 31.06181065596527,
        "winner": "REP",
        "color": "#cb181d"
      },
      "78": {
        "dem_votes": 11545,
        "rep_votes": 28530,
        "other_votes": 895,
        "total_votes": 40970,
        "dem_candidate": "Kathleen Clyde",
        "rep_candidate": "Frank LaRose",
        "margin": 16985,
        "margin_pct": 41.45716377837442,
        "winner": "REP",
        "color": "#cb181d"
      },
      "79": {
        "dem_votes": 11197,
        "rep_votes": 23225,
        "other_votes": 982,
        "total_votes": 35404,
        "dem_candidate": "Kathleen Clyde",
        "rep_candidate": "Frank LaRose",
        "margin": 12028,
        "margin_pct": 33.97356230934358,
        "winner": "REP",
        "color": "#cb181d"
      },
      "80": {
        "dem_votes": 12271,
        "rep_votes": 33718,
        "other_votes": 1260,
        "total_votes": 47249,
        "dem_candidate": "Kathleen Clyde",
        "rep_candidate": "Frank LaRose",
        "margin": 21447,
        "margin_pct": 45.391436855806475,
        "winner": "REP",
        "color": "#cb181d"
      },
      "81": {
        "dem_votes": 11875,
        "rep_votes": 27084,
        "other_votes": 1195,
        "total_votes": 40154,
        "dem_candidate": "Kathleen Clyde",
        "rep_candidate": "Frank LaRose",
        "margin": 15209,
        "margin_pct": 37.87667480201225,
        "winner": "REP",
        "color": "#cb181d"
      },
      "82": {
        "dem_votes": 10853,
        "rep_votes": 31440,
        "other_votes": 1023,
        "total_votes": 43316,
        "dem_candidate": "Kathleen Clyde",
        "rep_candidate": "Frank LaRose",
        "margin": 20587,
        "margin_pct": 47.527472527472526,
        "winner": "REP",
        "color": "#cb181d"
      },
      "83": {
        "dem_votes": 12391,
        "rep_votes": 29819,
        "other_votes": 1176,
        "total_votes": 43386,
        "dem_candidate": "Kathleen Clyde",
        "rep_candidate": "Frank LaRose",
        "margin": 17428,
        "margin_pct": 40.16963997602913,
        "winner": "REP",
        "color": "#cb181d"
      },
      "84": {
        "dem_votes": 8969,
        "rep_votes": 34444,
        "other_votes": 948,
        "total_votes": 44361,
        "dem_candidate": "Kathleen Clyde",
        "rep_candidate": "Frank LaRose",
        "margin": 25475,
        "margin_pct": 57.42656838213747,
        "winner": "REP",
        "color": "#cb181d"
      },
      "85": {
        "dem_votes": 10509,
        "rep_votes": 31819,
        "other_votes": 1148,
        "total_votes": 43476,
        "dem_candidate": "Kathleen Clyde",
        "rep_candidate": "Frank LaRose",
        "margin": 21310,
        "margin_pct": 49.01554880853804,
        "winner": "REP",
        "color": "#cb181d"
      },
      "86": {
        "dem_votes": 11182,
        "rep_votes": 21471,
        "other_votes": 906,
        "total_votes": 33559,
        "dem_candidate": "Kathleen Clyde",
        "rep_candidate": "Frank LaRose",
        "margin": 10289,
        "margin_pct": 30.659435620846864,
        "winner": "REP",
        "color": "#cb181d"
      },
      "87": {
        "dem_votes": 11094,
        "rep_votes": 27815,
        "other_votes": 1070,
        "total_votes": 39979,
        "dem_candidate": "Kathleen Clyde",
        "rep_candidate": "Frank LaRose",
        "margin": 16721,
        "margin_pct": 41.82445784036619,
        "winner": "REP",
        "color": "#cb181d"
      },
      "88": {
        "dem_votes": 15104,
        "rep_votes": 23840,
        "other_votes": 1283,
        "total_votes": 40227,
        "dem_candidate": "Kathleen Clyde",
        "rep_candidate": "Frank LaRose",
        "margin": 8736,
        "margin_pct": 21.716757401745095,
        "winner": "REP",
        "color": "#cb181d"
      },
      "89": {
        "dem_votes": 18633,
        "rep_votes": 23814,
        "other_votes": 1164,
        "total_votes": 43611,
        "dem_candidate": "Kathleen Clyde",
        "rep_candidate": "Frank LaRose",
        "margin": 5181,
        "margin_pct": 11.880030267593037,
        "winner": "REP",
        "color": "#fb6a4a"
      },
      "90": {
        "dem_votes": 12174,
        "rep_votes": 24018,
        "other_votes": 795,
        "total_votes": 36987,
        "dem_candidate": "Kathleen Clyde",
        "rep_candidate": "Frank LaRose",
        "margin": 11844,
        "margin_pct": 32.02206180549923,
        "winner": "REP",
        "color": "#cb181d"
      },
      "91": {
        "dem_votes": 10128,
        "rep_votes": 24037,
        "other_votes": 756,
        "total_votes": 34921,
        "dem_candidate": "Kathleen Clyde",
        "rep_candidate": "Frank LaRose",
        "margin": 13909,
        "margin_pct": 39.82990177829959,
        "winner": "REP",
        "color": "#cb181d"
      },
      "92": {
        "dem_votes": 13684,
        "rep_votes": 21480,
        "other_votes": 885,
        "total_votes": 36049,
        "dem_candidate": "Kathleen Clyde",
        "rep_candidate": "Frank LaRose",
        "margin": 7796,
        "margin_pct": 21.626120003328804,
        "winner": "REP",
        "color": "#cb181d"
      },
      "93": {
        "dem_votes": 12162,
        "rep_votes": 26705,
        "other_votes": 849,
        "total_votes": 39716,
        "dem_candidate": "Kathleen Clyde",
        "rep_candidate": "Frank LaRose",
        "margin": 14543,
        "margin_pct": 36.617484137375364,
        "winner": "REP",
        "color": "#cb181d"
      },
      "94": {
        "dem_votes": 19546,
        "rep_votes": 20165,
        "other_votes": 1108,
        "total_votes": 40819,
        "dem_candidate": "Kathleen Clyde",
        "rep_candidate": "Frank LaRose",
        "margin": 619,
        "margin_pct": 1.5164506724809523,
        "winner": "REP",
        "color": "#fcbba1"
      },
      "95": {
        "dem_votes": 14193,
        "rep_votes": 27548,
        "other_votes": 1010,
        "total_votes": 42751,
        "dem_candidate": "Kathleen Clyde",
        "rep_candidate": "Frank LaRose",
        "margin": 13355,
        "margin_pct": 31.239035344202478,
        "winner": "REP",
        "color": "#cb181d"
      },
      "96": {
        "dem_votes": 16810,
        "rep_votes": 23656,
        "other_votes": 933,
        "total_votes": 41399,
        "dem_candidate": "Kathleen Clyde",
        "rep_candidate": "Frank LaRose",
        "margin": 6846,
        "margin_pct": 16.53663131959709,
        "winner": "REP",
        "color": "#cb181d"
      },
      "97": {
        "dem_votes": 12641,
        "rep_votes": 23931,
        "other_votes": 986,
        "total_votes": 37558,
        "dem_candidate": "Kathleen Clyde",
        "rep_candidate": "Frank LaRose",
        "margin": 11290,
        "margin_pct": 30.060173598168166,
        "winner": "REP",
        "color": "#cb181d"
      },
      "98": {
        "dem_votes": 10271,
        "rep_votes": 23227,
        "other_votes": 805,
        "total_votes": 34303,
        "dem_candidate": "Kathleen Clyde",
        "rep_candidate": "Frank LaRose",
        "margin": 12956,
        "margin_pct": 37.76929131562837,
        "winner": "REP",
        "color": "#cb181d"
      },
      "99": {
        "dem_votes": 20769,
        "rep_votes": 27105,
        "other_votes": 1291,
        "total_votes": 49165,
        "dem_candidate": "Kathleen Clyde",
        "rep_candidate": "Frank LaRose",
        "margin": 6336,
        "margin_pct": 12.887216515814096,
        "winner": "REP",
        "color": "#fb6a4a"
      }
    }
  }
}
