{
  "scope": "state_house",
  "contest_type": "us_senate",
  "year": 2012,
  "general": {
    "results": {
      "1": {
        "dem_votes": 41873,
        "rep_votes": 8878,
        "other_votes": 1464,
        "total_votes": 52215,
        "dem_candidate": "Sherrod Brown",
        "rep_candidate": "Josh Mandel",
        "margin": -32995,
        "margin_pct": -63.190654026620706,
        "winner": "DEM",
        "color": "#2171b5"
      },
      "2": {
        "dem_votes": 34817,
        "rep_votes": 10271,
        "other_votes": 1626,
        "total_votes": 46714,
        "dem_candidate": "Sherrod Brown",
        "rep_candidate": "Josh Mandel",
        "margin": -24546,
        "margin_pct": -52.545275506272205,
        "winner": "DEM",
        "color": "#2171b5"
      },
      "3": {
        "dem_votes": 37163,
        "rep_votes": 7140,
        "other_votes": 1388,
        "total_votes": 45691,
        "dem_candidate": "Sherrod Brown",
        "rep_candidate": "Josh Mandel",
        "margin": -30023,
        "margin_pct": -65.70878291129544,
        "winner": "DEM",
        "color": "#2171b5"
      },
      "4": {
        "dem_votes": 26850,
        "rep_votes": 27274,
        "other_votes": 2307,
        "total_votes": 56431,
        "dem_candidate": "Sherrod Brown",
        "rep_candidate": "Josh Mandel",
        "margin": 424,
        "margin_pct": 0.7513600680477043,
        "winner": "REP",
        "color": "#fcbba1"
      },
      "5": {
        "dem_votes": 24969,
        "rep_votes": 20892,
        "other_votes": 2435,
        "total_votes": 48296,
        "dem_candidate": "Sherrod Brown",
        "rep_candidate": "Josh Mandel",
        "margin": -4077,
        "margin_pct": -8.441692893821434,
        "winner": "DEM",
        "color": "#6baed6"
      },
      "6": {
        "dem_votes": 22143,
        "rep_votes": 15462,
        "other_votes": 2163,
        "total_votes": 39768,
        "dem_candidate": "Sherrod Brown",
        "rep_candidate": "Josh Mandel",
        "margin": -6681,
        "margin_pct": -16.799939649969826,
        "winner": "DEM",
        "color": "#2171b5"
      },
      "7": {
        "dem_votes": 34826,
        "rep_votes": 21234,
        "other_votes": 1915,
        "total_votes": 57975,
        "dem_candidate": "Sherrod Brown",
        "rep_candidate": "Josh Mandel",
        "margin": -13592,
        "margin_pct": -23.444588184562313,
        "winner": "DEM",
        "color": "#2171b5"
      },
      "8": {
        "dem_votes": 33920,
        "rep_votes": 24059,
        "other_votes": 2325,
        "total_votes": 60304,
        "dem_candidate": "Sherrod Brown",
        "rep_candidate": "Josh Mandel",
        "margin": -9861,
        "margin_pct": -16.35214911117007,
        "winner": "DEM",
        "color": "#2171b5"
      },
      "9": {
        "dem_votes": 28524,
        "rep_votes": 14636,
        "other_votes": 1745,
        "total_votes": 44905,
        "dem_candidate": "Sherrod Brown",
        "rep_candidate": "Josh Mandel",
        "margin": -13888,
        "margin_pct": -30.92751363990647,
        "winner": "DEM",
        "color": "#2171b5"
      },
      "10": {
        "dem_votes": 24726,
        "rep_votes": 18463,
        "other_votes": 2206,
        "total_votes": 45395,
        "dem_candidate": "Sherrod Brown",
        "rep_candidate": "Josh Mandel",
        "margin": -6263,
        "margin_pct": -13.796673642471639,
        "winner": "DEM",
        "color": "#6baed6"
      },
      "11": {
        "dem_votes": 26489,
        "rep_votes": 27762,
        "other_votes": 2214,
        "total_votes": 56465,
        "dem_candidate": "Sherrod Brown",
        "rep_candidate": "Josh Mandel",
        "margin": 1273,
        "margin_pct": 2.2544939342955814,
        "winner": "REP",
        "color": "#fcbba1"
      },
      "12": {
        "dem_votes": 16204,
        "rep_votes": 22836,
        "other_votes": 2308,
        "total_votes": 41348,
        "dem_candidate": "Sherrod Brown",
        "rep_candidate": "Josh Mandel",
        "margin": 6632,
        "margin_pct": 16.039469865531586,
        "winner": "REP",
        "color": "#cb181d"
      },
      "13": {
        "dem_votes": 34345,
        "rep_votes": 10843,
        "other_votes": 2156,
        "total_votes": 47344,
        "dem_candidate": "Sherrod Brown",
        "rep_candidate": "Josh Mandel",
        "margin": -23502,
        "margin_pct": -49.64092598850963,
        "winner": "DEM",
        "color": "#2171b5"
      },
      "14": {
        "dem_votes": 29125,
        "rep_votes": 17083,
        "other_votes": 2796,
        "total_votes": 49004,
        "dem_candidate": "Sherrod Brown",
        "rep_candidate": "Josh Mandel",
        "margin": -12042,
        "margin_pct": -24.57350420373847,
        "winner": "DEM",
        "color": "#2171b5"
      },
      "15": {
        "dem_votes": 30894,
        "rep_votes": 22076,
        "other_votes": 2555,
        "total_votes": 55525,
        "dem_candidate": "Sherrod Brown",
        "rep_candidate": "Josh Mandel",
        "margin": -8818,
        "margin_pct": -15.881134624043225,
        "winner": "DEM",
        "color": "#2171b5"
      },
      "16": {
        "dem_votes": 31589,
        "rep_votes": 26086,
        "other_votes": 2410,
        "total_votes": 60085,
        "dem_candidate": "Sherrod Brown",
        "rep_candidate": "Josh Mandel",
        "margin": -5503,
        "margin_pct": -9.158691853207955,
        "winner": "DEM",
        "color": "#6baed6"
      },
      "17": {
        "dem_votes": 30689,
        "rep_votes": 24504,
        "other_votes": 2409,
        "total_votes": 57602,
        "dem_candidate": "Sherrod Brown",
        "rep_candidate": "Josh Mandel",
        "margin": -6185,
        "margin_pct": -10.737474393250235,
        "winner": "DEM",
        "color": "#6baed6"
      },
      "18": {
        "dem_votes": 55087,
        "rep_votes": 4672,
        "other_votes": 1233,
        "total_votes": 60992,
        "dem_candidate": "Sherrod Brown",
        "rep_candidate": "Josh Mandel",
        "margin": -50415,
        "margin_pct": -82.6583814270724,
        "winner": "DEM",
        "color": "#2171b5"
      },
      "19": {
        "dem_votes": 36719,
        "rep_votes": 22253,
        "other_votes": 1796,
        "total_votes": 60768,
        "dem_candidate": "Sherrod Brown",
        "rep_candidate": "Josh Mandel",
        "margin": -14466,
        "margin_pct": -23.80529225908373,
        "winner": "DEM",
        "color": "#2171b5"
      },
      "20": {
        "dem_votes": 44854,
        "rep_votes": 3577,
        "other_votes": 1119,
        "total_votes": 49550,
        "dem_candidate": "Sherrod Brown",
        "rep_candidate": "Josh Mandel",
        "margin": -41277,
        "margin_pct": -83.30373360242179,
        "winner": "DEM",
        "color": "#2171b5"
      },
      "21": {
        "dem_votes": 44089,
        "rep_votes": 13729,
        "other_votes": 1534,
        "total_votes": 59352,
        "dem_candidate": "Sherrod Brown",
        "rep_candidate": "Josh Mandel",
        "margin": -30360,
        "margin_pct": -51.15244642135058,
        "winner": "DEM",
        "color": "#2171b5"
      },
      "22": {
        "dem_votes": 54616,
        "rep_votes": 7863,
        "other_votes": 873,
        "total_votes": 63352,
        "dem_candidate": "Sherrod Brown",
        "rep_candidate": "Josh Mandel",
        "margin": -46753,
        "margin_pct": -73.79877509786589,
        "winner": "DEM",
        "color": "#2171b5"
      },
      "23": {
        "dem_votes": 31647,
        "rep_votes": 24506,
        "other_votes": 2990,
        "total_votes": 59143,
        "dem_candidate": "Sherrod Brown",
        "rep_candidate": "Josh Mandel",
        "margin": -7141,
        "margin_pct": -12.074125424817815,
        "winner": "DEM",
        "color": "#6baed6"
      },
      "24": {
        "dem_votes": 32675,
        "rep_votes": 13384,
        "other_votes": 1675,
        "total_votes": 47734,
        "dem_candidate": "Sherrod Brown",
        "rep_candidate": "Josh Mandel",
        "margin": -19291,
        "margin_pct": -40.41354171031131,
        "winner": "DEM",
        "color": "#2171b5"
      },
      "25": {
        "dem_votes": 35292,
        "rep_votes": 10798,
        "other_votes": 1464,
        "total_votes": 47554,
        "dem_candidate": "Sherrod Brown",
        "rep_candidate": "Josh Mandel",
        "margin": -24494,
        "margin_pct": -51.50775959961307,
        "winner": "DEM",
        "color": "#2171b5"
      },
      "26": {
        "dem_votes": 45634,
        "rep_votes": 18712,
        "other_votes": 1836,
        "total_votes": 66182,
        "dem_candidate": "Sherrod Brown",
        "rep_candidate": "Josh Mandel",
        "margin": -26922,
        "margin_pct": -40.67873439908132,
        "winner": "DEM",
        "color": "#2171b5"
      },
      "27": {
        "dem_votes": 34250,
        "rep_votes": 34504,
        "other_votes": 2042,
        "total_votes": 70796,
        "dem_candidate": "Sherrod Brown",
        "rep_candidate": "Josh Mandel",
        "margin": 254,
        "margin_pct": 0.3587773320526583,
        "winner": "REP",
        "color": "#fcbba1"
      },
      "28": {
        "dem_votes": 30129,
        "rep_votes": 29413,
        "other_votes": 2245,
        "total_votes": 61787,
        "dem_candidate": "Sherrod Brown",
        "rep_candidate": "Josh Mandel",
        "margin": -716,
        "margin_pct": -1.1588198164662469,
        "winner": "DEM",
        "color": "#c6dbef"
      },
      "29": {
        "dem_votes": 22720,
        "rep_votes": 28190,
        "other_votes": 2309,
        "total_votes": 53219,
        "dem_candidate": "Sherrod Brown",
        "rep_candidate": "Josh Mandel",
        "margin": 5470,
        "margin_pct": 10.278284071478232,
        "winner": "REP",
        "color": "#fb6a4a"
      },
      "30": {
        "dem_votes": 17624,
        "rep_votes": 39693,
        "other_votes": 2723,
        "total_votes": 60040,
        "dem_candidate": "Sherrod Brown",
        "rep_candidate": "Josh Mandel",
        "margin": 22069,
        "margin_pct": 36.757161892071956,
        "winner": "REP",
        "color": "#cb181d"
      },
      "31": {
        "dem_votes": 33064,
        "rep_votes": 28858,
        "other_votes": 2699,
        "total_votes": 64621,
        "dem_candidate": "Sherrod Brown",
        "rep_candidate": "Josh Mandel",
        "margin": -4206,
        "margin_pct": -6.508720075517246,
        "winner": "DEM",
        "color": "#6baed6"
      },
      "32": {
        "dem_votes": 30769,
        "rep_votes": 20206,
        "other_votes": 3218,
        "total_votes": 54193,
        "dem_candidate": "Sherrod Brown",
        "rep_candidate": "Josh Mandel",
        "margin": -10563,
        "margin_pct": -19.491447234882735,
        "winner": "DEM",
        "color": "#2171b5"
      },
      "33": {
        "dem_votes": 42041,
        "rep_votes": 9684,
        "other_votes": 2083,
        "total_votes": 53808,
        "dem_candidate": "Sherrod Brown",
        "rep_candidate": "Josh Mandel",
        "margin": -32357,
        "margin_pct": -60.13418079096046,
        "winner": "DEM",
        "color": "#2171b5"
      },
      "34": {
        "dem_votes": 31721,
        "rep_votes": 28366,
        "other_votes": 2820,
        "total_votes": 62907,
        "dem_candidate": "Sherrod Brown",
        "rep_candidate": "Josh Mandel",
        "margin": -3355,
        "margin_pct": -5.333269747404899,
        "winner": "DEM",
        "color": "#6baed6"
      },
      "35": {
        "dem_votes": 28211,
        "rep_votes": 28232,
        "other_votes": 3512,
        "total_votes": 59955,
        "dem_candidate": "Sherrod Brown",
        "rep_candidate": "Josh Mandel",
        "margin": 21,
        "margin_pct": 0.03502626970227671,
        "winner": "REP",
        "color": "#fcbba1"
      },
      "36": {
        "dem_votes": 27813,
        "rep_votes": 25798,
        "other_votes": 2294,
        "total_votes": 55905,
        "dem_candidate": "Sherrod Brown",
        "rep_candidate": "Josh Mandel",
        "margin": -2015,
        "margin_pct": -3.6043287720239694,
        "winner": "DEM",
        "color": "#c6dbef"
      },
      "37": {
        "dem_votes": 22871,
        "rep_votes": 36369,
        "other_votes": 2245,
        "total_votes": 61485,
        "dem_candidate": "Sherrod Brown",
        "rep_candidate": "Josh Mandel",
        "margin": 13498,
        "margin_pct": 21.95332194844271,
        "winner": "REP",
        "color": "#cb181d"
      },
      "38": {
        "dem_votes": 36071,
        "rep_votes": 12533,
        "other_votes": 1642,
        "total_votes": 50246,
        "dem_candidate": "Sherrod Brown",
        "rep_candidate": "Josh Mandel",
        "margin": -23538,
        "margin_pct": -46.845520041396334,
        "winner": "DEM",
        "color": "#2171b5"
      },
      "39": {
        "dem_votes": 35280,
        "rep_votes": 26998,
        "other_votes": 2272,
        "total_votes": 64550,
        "dem_candidate": "Sherrod Brown",
        "rep_candidate": "Josh Mandel",
        "margin": -8282,
        "margin_pct": -12.830364058869092,
        "winner": "DEM",
        "color": "#6baed6"
      },
      "40": {
        "dem_votes": 19285,
        "rep_votes": 31675,
        "other_votes": 2584,
        "total_votes": 53544,
        "dem_candidate": "Sherrod Brown",
        "rep_candidate": "Josh Mandel",
        "margin": 12390,
        "margin_pct": 23.13984760197221,
        "winner": "REP",
        "color": "#cb181d"
      },
      "41": {
        "dem_votes": 27472,
        "rep_votes": 19640,
        "other_votes": 2264,
        "total_votes": 49376,
        "dem_candidate": "Sherrod Brown",
        "rep_candidate": "Josh Mandel",
        "margin": -7832,
        "margin_pct": -15.86195722618276,
        "winner": "DEM",
        "color": "#2171b5"
      },
      "42": {
        "dem_votes": 27492,
        "rep_votes": 20492,
        "other_votes": 2287,
        "total_votes": 50271,
        "dem_candidate": "Sherrod Brown",
        "rep_candidate": "Josh Mandel",
        "margin": -7000,
        "margin_pct": -13.92452905253526,
        "winner": "DEM",
        "color": "#6baed6"
      },
      "43": {
        "dem_votes": 33404,
        "rep_votes": 14080,
        "other_votes": 2046,
        "total_votes": 49530,
        "dem_candidate": "Sherrod Brown",
        "rep_candidate": "Josh Mandel",
        "margin": -19324,
        "margin_pct": -39.0147385422976,
        "winner": "DEM",
        "color": "#2171b5"
      },
      "44": {
        "dem_votes": 35332,
        "rep_votes": 8294,
        "other_votes": 1500,
        "total_votes": 45126,
        "dem_candidate": "Sherrod Brown",
        "rep_candidate": "Josh Mandel",
        "margin": -27038,
        "margin_pct": -59.916677746753535,
        "winner": "DEM",
        "color": "#2171b5"
      },
      "45": {
        "dem_votes": 20023,
        "rep_votes": 34607,
        "other_votes": 2276,
        "total_votes": 56906,
        "dem_candidate": "Sherrod Brown",
        "rep_candidate": "Josh Mandel",
        "margin": 14584,
        "margin_pct": 25.628229009243313,
        "winner": "REP",
        "color": "#cb181d"
      },
      "46": {
        "dem_votes": 17719,
        "rep_votes": 27675,
        "other_votes": 2261,
        "total_votes": 47655,
        "dem_candidate": "Sherrod Brown",
        "rep_candidate": "Josh Mandel",
        "margin": 9956,
        "margin_pct": 20.891826670863498,
        "winner": "REP",
        "color": "#cb181d"
      },
      "47": {
        "dem_votes": 18977,
        "rep_votes": 25879,
        "other_votes": 2227,
        "total_votes": 47083,
        "dem_candidate": "Sherrod Brown",
        "rep_candidate": "Josh Mandel",
        "margin": 6902,
        "margin_pct": 14.659218826327974,
        "winner": "REP",
        "color": "#fb6a4a"
      },
      "48": {
        "dem_votes": 26559,
        "rep_votes": 30106,
        "other_votes": 3442,
        "total_votes": 60107,
        "dem_candidate": "Sherrod Brown",
        "rep_candidate": "Josh Mandel",
        "margin": 3547,
        "margin_pct": 5.901142961718269,
        "winner": "REP",
        "color": "#fb6a4a"
      },
      "49": {
        "dem_votes": 27431,
        "rep_votes": 18511,
        "other_votes": 2718,
        "total_votes": 48660,
        "dem_candidate": "Sherrod Brown",
        "rep_candidate": "Josh Mandel",
        "margin": -8920,
        "margin_pct": -18.33127825729552,
        "winner": "DEM",
        "color": "#2171b5"
      },
      "50": {
        "dem_votes": 26431,
        "rep_votes": 23083,
        "other_votes": 3700,
        "total_votes": 53214,
        "dem_candidate": "Sherrod Brown",
        "rep_candidate": "Josh Mandel",
        "margin": -3348,
        "margin_pct": -6.291577404442441,
        "winner": "DEM",
        "color": "#6baed6"
      },
      "51": {
        "dem_votes": 21964,
        "rep_votes": 24792,
        "other_votes": 3345,
        "total_votes": 50101,
        "dem_candidate": "Sherrod Brown",
        "rep_candidate": "Josh Mandel",
        "margin": 2828,
        "margin_pct": 5.644597912217321,
        "winner": "REP",
        "color": "#fb6a4a"
      },
      "52": {
        "dem_votes": 25760,
        "rep_votes": 17121,
        "other_votes": 1989,
        "total_votes": 44870,
        "dem_candidate": "Sherrod Brown",
        "rep_candidate": "Josh Mandel",
        "margin": -8639,
        "margin_pct": -19.253398707376867,
        "winner": "DEM",
        "color": "#2171b5"
      },
      "53": {
        "dem_votes": 31821,
        "rep_votes": 18827,
        "other_votes": 2351,
        "total_votes": 52999,
        "dem_candidate": "Sherrod Brown",
        "rep_candidate": "Josh Mandel",
        "margin": -12994,
        "margin_pct": -24.517443725353306,
        "winner": "DEM",
        "color": "#2171b5"
      },
      "54": {
        "dem_votes": 29022,
        "rep_votes": 24560,
        "other_votes": 3212,
        "total_votes": 56794,
        "dem_candidate": "Sherrod Brown",
        "rep_candidate": "Josh Mandel",
        "margin": -4462,
        "margin_pct": -7.856463710955383,
        "winner": "DEM",
        "color": "#6baed6"
      },
      "55": {
        "dem_votes": 16135,
        "rep_votes": 36976,
        "other_votes": 2526,
        "total_votes": 55637,
        "dem_candidate": "Sherrod Brown",
        "rep_candidate": "Josh Mandel",
        "margin": 20841,
        "margin_pct": 37.45888527418804,
        "winner": "REP",
        "color": "#cb181d"
      },
      "56": {
        "dem_votes": 17230,
        "rep_votes": 33028,
        "other_votes": 1953,
        "total_votes": 52211,
        "dem_candidate": "Sherrod Brown",
        "rep_candidate": "Josh Mandel",
        "margin": 15798,
        "margin_pct": 30.25799161096321,
        "winner": "REP",
        "color": "#cb181d"
      },
      "57": {
        "dem_votes": 27393,
        "rep_votes": 29920,
        "other_votes": 3193,
        "total_votes": 60506,
        "dem_candidate": "Sherrod Brown",
        "rep_candidate": "Josh Mandel",
        "margin": 2527,
        "margin_pct": 4.176445311208806,
        "winner": "REP",
        "color": "#fcbba1"
      },
      "58": {
        "dem_votes": 33305,
        "rep_votes": 16098,
        "other_votes": 2388,
        "total_votes": 51791,
        "dem_candidate": "Sherrod Brown",
        "rep_candidate": "Josh Mandel",
        "margin": -17207,
        "margin_pct": -33.22391921376301,
        "winner": "DEM",
        "color": "#2171b5"
      },
      "59": {
        "dem_votes": 27613,
        "rep_votes": 15464,
        "other_votes": 2238,
        "total_votes": 45315,
        "dem_candidate": "Sherrod Brown",
        "rep_candidate": "Josh Mandel",
        "margin": -12149,
        "margin_pct": -26.810107028577733,
        "winner": "DEM",
        "color": "#2171b5"
      },
      "60": {
        "dem_votes": 20337,
        "rep_votes": 29817,
        "other_votes": 2315,
        "total_votes": 52469,
        "dem_candidate": "Sherrod Brown",
        "rep_candidate": "Josh Mandel",
        "margin": 9480,
        "margin_pct": 18.067811469629685,
        "winner": "REP",
        "color": "#cb181d"
      },
      "61": {
        "dem_votes": 19642,
        "rep_votes": 30620,
        "other_votes": 2143,
        "total_votes": 52405,
        "dem_candidate": "Sherrod Brown",
        "rep_candidate": "Josh Mandel",
        "margin": 10978,
        "margin_pct": 20.948382787901917,
        "winner": "REP",
        "color": "#cb181d"
      },
      "62": {
        "dem_votes": 17174,
        "rep_votes": 33414,
        "other_votes": 2629,
        "total_votes": 53217,
        "dem_candidate": "Sherrod Brown",
        "rep_candidate": "Josh Mandel",
        "margin": 16240,
        "margin_pct": 30.516564255782924,
        "winner": "REP",
        "color": "#cb181d"
      },
      "63": {
        "dem_votes": 13363,
        "rep_votes": 25167,
        "other_votes": 2221,
        "total_votes": 40751,
        "dem_candidate": "Sherrod Brown",
        "rep_candidate": "Josh Mandel",
        "margin": 11804,
        "margin_pct": 28.96616033962357,
        "winner": "REP",
        "color": "#cb181d"
      },
      "64": {
        "dem_votes": 31652,
        "rep_votes": 13317,
        "other_votes": 2263,
        "total_votes": 47232,
        "dem_candidate": "Sherrod Brown",
        "rep_candidate": "Josh Mandel",
        "margin": -18335,
        "margin_pct": -38.81902100271002,
        "winner": "DEM",
        "color": "#2171b5"
      },
      "65": {
        "dem_votes": 24300,
        "rep_votes": 20333,
        "other_votes": 3123,
        "total_votes": 47756,
        "dem_candidate": "Sherrod Brown",
        "rep_candidate": "Josh Mandel",
        "margin": -3967,
        "margin_pct": -8.30680961554569,
        "winner": "DEM",
        "color": "#6baed6"
      },
      "66": {
        "dem_votes": 21544,
        "rep_votes": 27156,
        "other_votes": 2559,
        "total_votes": 51259,
        "dem_candidate": "Sherrod Brown",
        "rep_candidate": "Josh Mandel",
        "margin": 5612,
        "margin_pct": 10.94832127041105,
        "winner": "REP",
        "color": "#fb6a4a"
      },
      "67": {
        "dem_votes": 19863,
        "rep_votes": 24669,
        "other_votes": 2844,
        "total_votes": 47376,
        "dem_candidate": "Sherrod Brown",
        "rep_candidate": "Josh Mandel",
        "margin": 4806,
        "margin_pct": 10.144376899696049,
        "winner": "REP",
        "color": "#fb6a4a"
      },
      "68": {
        "dem_votes": 17501,
        "rep_votes": 22286,
        "other_votes": 2280,
        "total_votes": 42067,
        "dem_candidate": "Sherrod Brown",
        "rep_candidate": "Josh Mandel",
        "margin": 4785,
        "margin_pct": 11.37471176932037,
        "winner": "REP",
        "color": "#fb6a4a"
      },
      "69": {
        "dem_votes": 18648,
        "rep_votes": 26751,
        "other_votes": 2793,
        "total_votes": 48192,
        "dem_candidate": "Sherrod Brown",
        "rep_candidate": "Josh Mandel",
        "margin": 8103,
        "margin_pct": 16.81399402390438,
        "winner": "REP",
        "color": "#cb181d"
      },
      "70": {
        "dem_votes": 20827,
        "rep_votes": 33539,
        "other_votes": 2172,
        "total_votes": 56538,
        "dem_candidate": "Sherrod Brown",
        "rep_candidate": "Josh Mandel",
        "margin": 12712,
        "margin_pct": 22.48399306661007,
        "winner": "REP",
        "color": "#cb181d"
      },
      "71": {
        "dem_votes": 20604,
        "rep_votes": 29877,
        "other_votes": 2448,
        "total_votes": 52929,
        "dem_candidate": "Sherrod Brown",
        "rep_candidate": "Josh Mandel",
        "margin": 9273,
        "margin_pct": 17.51969619679193,
        "winner": "REP",
        "color": "#cb181d"
      },
      "72": {
        "dem_votes": 28161,
        "rep_votes": 22650,
        "other_votes": 3168,
        "total_votes": 53979,
        "dem_candidate": "Sherrod Brown",
        "rep_candidate": "Josh Mandel",
        "margin": -5511,
        "margin_pct": -10.209525926749292,
        "winner": "DEM",
        "color": "#6baed6"
      },
      "73": {
        "dem_votes": 22201,
        "rep_votes": 27094,
        "other_votes": 2554,
        "total_votes": 51849,
        "dem_candidate": "Sherrod Brown",
        "rep_candidate": "Josh Mandel",
        "margin": 4893,
        "margin_pct": 9.437019036046983,
        "winner": "REP",
        "color": "#fb6a4a"
      },
      "74": {
        "dem_votes": 20122,
        "rep_votes": 17535,
        "other_votes": 1834,
        "total_votes": 39491,
        "dem_candidate": "Sherrod Brown",
        "rep_candidate": "Josh Mandel",
        "margin": -2587,
        "margin_pct": -6.550859689549518,
        "winner": "DEM",
        "color": "#6baed6"
      },
      "75": {
        "dem_votes": 26336,
        "rep_votes": 23552,
        "other_votes": 2507,
        "total_votes": 52395,
        "dem_candidate": "Sherrod Brown",
        "rep_candidate": "Josh Mandel",
        "margin": -2784,
        "margin_pct": -5.313484111079301,
        "winner": "DEM",
        "color": "#6baed6"
      },
      "76": {
        "dem_votes": 23358,
        "rep_votes": 30194,
        "other_votes": 2688,
        "total_votes": 56240,
        "dem_candidate": "Sherrod Brown",
        "rep_candidate": "Josh Mandel",
        "margin": 6836,
        "margin_pct": 12.155049786628734,
        "winner": "REP",
        "color": "#fb6a4a"
      },
      "77": {
        "dem_votes": 16027,
        "rep_votes": 23382,
        "other_votes": 2404,
        "total_votes": 41813,
        "dem_candidate": "Sherrod Brown",
        "rep_candidate": "Josh Mandel",
        "margin": 7355,
        "margin_pct": 17.590223136345156,
        "winner": "REP",
        "color": "#cb181d"
      },
      "78": {
        "dem_votes": 18819,
        "rep_votes": 33355,
        "other_votes": 1779,
        "total_votes": 53953,
        "dem_candidate": "Sherrod Brown",
        "rep_candidate": "Josh Mandel",
        "margin": 14536,
        "margin_pct": 26.941968009193186,
        "winner": "REP",
        "color": "#cb181d"
      },
      "79": {
        "dem_votes": 19787,
        "rep_votes": 21333,
        "other_votes": 3264,
        "total_votes": 44384,
        "dem_candidate": "Sherrod Brown",
        "rep_candidate": "Josh Mandel",
        "margin": 1546,
        "margin_pct": 3.48323720259553,
        "winner": "REP",
        "color": "#fcbba1"
      },
      "80": {
        "dem_votes": 17849,
        "rep_votes": 38397,
        "other_votes": 2514,
        "total_votes": 58760,
        "dem_candidate": "Sherrod Brown",
        "rep_candidate": "Josh Mandel",
        "margin": 20548,
        "margin_pct": 34.96936691626957,
        "winner": "REP",
        "color": "#cb181d"
      },
      "81": {
        "dem_votes": 20348,
        "rep_votes": 28755,
        "other_votes": 3154,
        "total_votes": 52257,
        "dem_candidate": "Sherrod Brown",
        "rep_candidate": "Josh Mandel",
        "margin": 8407,
        "margin_pct": 16.08779685018275,
        "winner": "REP",
        "color": "#cb181d"
      },
      "82": {
        "dem_votes": 17837,
        "rep_votes": 35201,
        "other_votes": 2726,
        "total_votes": 55764,
        "dem_candidate": "Sherrod Brown",
        "rep_candidate": "Josh Mandel",
        "margin": 17364,
        "margin_pct": 31.1383688401119,
        "winner": "REP",
        "color": "#cb181d"
      },
      "83": {
        "dem_votes": 17015,
        "rep_votes": 30862,
        "other_votes": 2726,
        "total_votes": 50603,
        "dem_candidate": "Sherrod Brown",
        "rep_candidate": "Josh Mandel",
        "margin": 13847,
        "margin_pct": 27.36399027725629,
        "winner": "REP",
        "color": "#cb181d"
      },
      "84": {
        "dem_votes": 13539,
        "rep_votes": 39266,
        "other_votes": 2447,
        "total_votes": 55252,
        "dem_candidate": "Sherrod Brown",
        "rep_candidate": "Josh Mandel",
        "margin": 25727,
        "margin_pct": 46.563020343154996,
        "winner": "REP",
        "color": "#cb181d"
      },
      "85": {
        "dem_votes": 16438,
        "rep_votes": 34420,
        "other_votes": 2926,
        "total_votes": 53784,
        "dem_candidate": "Sherrod Brown",
        "rep_candidate": "Josh Mandel",
        "margin": 17982,
        "margin_pct": 33.433734939759034,
        "winner": "REP",
        "color": "#cb181d"
      },
      "86": {
        "dem_votes": 13090,
        "rep_votes": 21006,
        "other_votes": 2149,
        "total_votes": 36245,
        "dem_candidate": "Sherrod Brown",
        "rep_candidate": "Josh Mandel",
        "margin": 7916,
        "margin_pct": 21.84025382811422,
        "winner": "REP",
        "color": "#cb181d"
      },
      "87": {
        "dem_votes": 16732,
        "rep_votes": 27164,
        "other_votes": 3067,
        "total_votes": 46963,
        "dem_candidate": "Sherrod Brown",
        "rep_candidate": "Josh Mandel",
        "margin": 10432,
        "margin_pct": 22.213231693034942,
        "winner": "REP",
        "color": "#cb181d"
      },
      "88": {
        "dem_votes": 23871,
        "rep_votes": 25747,
        "other_votes": 3438,
        "total_votes": 53056,
        "dem_candidate": "Sherrod Brown",
        "rep_candidate": "Josh Mandel",
        "margin": 1876,
        "margin_pct": 3.5358866103739444,
        "winner": "REP",
        "color": "#fcbba1"
      },
      "89": {
        "dem_votes": 26935,
        "rep_votes": 23461,
        "other_votes": 3047,
        "total_votes": 53443,
        "dem_candidate": "Sherrod Brown",
        "rep_candidate": "Josh Mandel",
        "margin": -3474,
        "margin_pct": -6.500383586250772,
        "winner": "DEM",
        "color": "#6baed6"
      },
      "90": {
        "dem_votes": 20171,
        "rep_votes": 20806,
        "other_votes": 2118,
        "total_votes": 43095,
        "dem_candidate": "Sherrod Brown",
        "rep_candidate": "Josh Mandel",
        "margin": 635,
        "margin_pct": 1.473488803805546,
        "winner": "REP",
        "color": "#fcbba1"
      },
      "91": {
        "dem_votes": 17781,
        "rep_votes": 24390,
        "other_votes": 2363,
        "total_votes": 44534,
        "dem_candidate": "Sherrod Brown",
        "rep_candidate": "Josh Mandel",
        "margin": 6609,
        "margin_pct": 14.840346701396687,
        "winner": "REP",
        "color": "#fb6a4a"
      },
      "92": {
        "dem_votes": 19427,
        "rep_votes": 19483,
        "other_votes": 2372,
        "total_votes": 41282,
        "dem_candidate": "Sherrod Brown",
        "rep_candidate": "Josh Mandel",
        "margin": 56,
        "margin_pct": 0.1356523424252701,
        "winner": "REP",
        "color": "#fcbba1"
      },
      "93": {
        "dem_votes": 20281,
        "rep_votes": 25143,
        "other_votes": 2134,
        "total_votes": 47558,
        "dem_candidate": "Sherrod Brown",
        "rep_candidate": "Josh Mandel",
        "margin": 4862,
        "margin_pct": 10.223306278649229,
        "winner": "REP",
        "color": "#fb6a4a"
      },
      "94": {
        "dem_votes": 25009,
        "rep_votes": 19264,
        "other_votes": 2313,
        "total_votes": 46586,
        "dem_candidate": "Sherrod Brown",
        "rep_candidate": "Josh Mandel",
        "margin": -5745,
        "margin_pct": -12.332031082299403,
        "winner": "DEM",
        "color": "#6baed6"
      },
      "95": {
        "dem_votes": 20616,
        "rep_votes": 26787,
        "other_votes": 2448,
        "total_votes": 49851,
        "dem_candidate": "Sherrod Brown",
        "rep_candidate": "Josh Mandel",
        "margin": 6171,
        "margin_pct": 12.378889089486671,
        "winner": "REP",
        "color": "#fb6a4a"
      },
      "96": {
        "dem_votes": 25540,
        "rep_votes": 21615,
        "other_votes": 2364,
        "total_votes": 49519,
        "dem_candidate": "Sherrod Brown",
        "rep_candidate": "Josh Mandel",
        "margin": -3925,
        "margin_pct": -7.926250530099558,
        "winner": "DEM",
        "color": "#6baed6"
      },
      "97": {
        "dem_votes": 20714,
        "rep_votes": 24654,
        "other_votes": 2962,
        "total_votes": 48330,
        "dem_candidate": "Sherrod Brown",
        "rep_candidate": "Josh Mandel",
        "margin": 3940,
        "margin_pct": 8.152286364576868,
        "winner": "REP",
        "color": "#fb6a4a"
      },
      "98": {
        "dem_votes": 14381,
        "rep_votes": 23665,
        "other_votes": 2501,
        "total_votes": 40547,
        "dem_candidate": "Sherrod Brown",
        "rep_candidate": "Josh Mandel",
        "margin": 9284,
        "margin_pct": 22.89688509630799,
        "winner": "REP",
        "color": "#cb181d"
      },
      "99": {
        "dem_votes": 22834,
        "rep_votes": 23818,
        "other_votes": 2703,
        "total_votes": 49355,
        "dem_candidate": "Sherrod Brown",
        "rep_candidate": "Josh Mandel",
        "margin": 984,
        "margin_pct": 1.9937189747745923,
        "winner": "REP",
        "color": "#fcbba1"
      }
    }
  }
}
