{
  "scope": "congressional",
  "contest_type": "justice_of_the_supreme_court_unexpired_term_ending_12_31_2014",
  "year": 2012,
  "general": {
    "results": {
      "1": {
        "dem_votes": 0,
        "rep_votes": 0,
        "other_votes": 286592,
        "total_votes": 286592,
        "dem_candidate": "",
        "rep_candidate": "",
        "margin": 0,
        "margin_pct": 0.0,
        "winner": "TIE",
        "color": "#d9d9d9"
      },
      "2": {
        "dem_votes": 0,
        "rep_votes": 0,
        "other_votes": 233229,
        "total_votes": 233229,
        "dem_candidate": "",
        "rep_candidate": "",
        "margin": 0,
        "margin_pct": 0.0,
        "winner": "TIE",
        "color": "#d9d9d9"
      },
      "3": {
        "dem_votes": 0,
        "rep_votes": 0,
        "other_votes": 275064,
        "total_votes": 275064,
        "dem_candidate": "",
        "rep_candidate": "",
        "margin": 0,
        "margin_pct": 0.0,
        "winner": "TIE",
        "color": "#d9d9d9"
      },
      "4": {
        "dem_votes": 0,
        "rep_votes": 0,
        "other_votes": 253164,
        "total_votes": 253164,
        "dem_candidate": "",
        "rep_candidate": "",
        "margin": 0,
        "margin_pct": 0.0,
        "winner": "TIE",
        "color": "#d9d9d9"
      },
      "5": {
        "dem_votes": 0,
        "rep_votes": 0,
        "other_votes": 252206,
        "total_votes": 252206,
        "dem_candidate": "",
        "rep_candidate": "",
        "margin": 0,
        "margin_pct": 0.0,
        "winner": "TIE",
        "color": "#d9d9d9"
      },
      "6": {
        "dem_votes": 0,
        "rep_votes": 0,
        "other_votes": 254135,
        "total_votes": 254135,
        "dem_candidate": "",
        "rep_candidate": "",
        "margin": 0,
        "margin_pct": 0.0,
        "winner": "TIE",
        "color": "#d9d9d9"
      },
      "7": {
        "dem_votes": 0,
        "rep_votes": 0,
        "other_votes": 233810,
        "total_votes": 233810,
        "dem_candidate": "",
        "rep_candidate": "",
        "margin": 0,
        "margin_pct": 0.0,
        "winner": "TIE",
        "color": "#d9d9d9"
      },
      "8": {
        "dem_votes": 0,
        "rep_votes": 0,
        "other_votes": 271848,
        "total_votes": 271848,
        "dem_candidate": "",
        "rep_candidate": "",
        "margin": 0,
        "margin_pct": 0.0,
        "winner": "TIE",
        "color": "#d9d9d9"
      },
      "9": {
        "dem_votes": 0,
        "rep_votes": 0,
        "other_votes": 252450,
        "total_votes": 252450,
        "dem_candidate": "",
        "rep_candidate": "",
        "margin": 0,
        "margin_pct": 0.0,
        "winner": "TIE",
        "color": "#d9d9d9"
      },
      "10": {
        "dem_votes": 0,
        "rep_votes": 0,
        "other_votes": 283666,
        "total_votes": 283666,
        "dem_candidate": "",
        "rep_candidate": "",
        "margin": 0,
        "margin_pct": 0.0,
        "winner": "TIE",
        "color": "#d9d9d9"
      },
      "11": {
        "dem_votes": 0,
        "rep_votes": 0,
        "other_votes": 259080,
        "total_votes": 259080,
        "dem_candidate": "",
        "rep_candidate": "",
        "margin": 0,
        "margin_pct": 0.0,
        "winner": "TIE",
        "color": "#d9d9d9"
      },
      "12": {
        "dem_votes": 0,
        "rep_votes": 0,
        "other_votes": 236700,
        "total_votes": 236700,
        "dem_candidate": "",
        "rep_candidate": "",
        "margin": 0,
        "margin_pct": 0.0,
        "winner": "TIE",
        "color": "#d9d9d9"
      },
      "13": {
        "dem_votes": 0,
        "rep_votes": 0,
        "other_votes": 289477,
        "total_votes": 289477,
        "dem_candidate": "",
        "rep_candidate": "",
        "margin": 0,
        "margin_pct": 0.0,
        "winner": "TIE",
        "color": "#d9d9d9"
      },
      "14": {
        "dem_votes": 0,
        "rep_votes": 0,
        "other_votes": 253530,
        "total_votes": 253530,
        "dem_candidate": "",
        "rep_candidate": "",
        "margin": 0,
        "margin_pct": 0.0,
        "winner": "TIE",
        "color": "#d9d9d9"
      },
      "15": {
        "dem_votes": 0,
        "rep_votes": 0,
        "other_votes": 241979,
        "total_votes": 241979,
        "dem_candidate": "",
        "rep_candidate": "",
        "margin": 0,
        "margin_pct": 0.0,
        "winner": "TIE",
        "color": "#d9d9d9"
      }
    }
  }
}
