{
  "scope": "state_house",
  "contest_type": "treasurer",
  "year": 2014,
  "general": {
    "results": {
      "1": {
        "dem_votes": 15662,
        "rep_votes": 5372,
        "other_votes": 0,
        "total_votes": 21034,
        "dem_candidate": "Connie Pillich",
        "rep_candidate": "Josh Mandel",
        "margin": -10290,
        "margin_pct": -48.920794903489586,
        "winner": "DEM",
        "color": "#2171b5"
      },
      "2": {
        "dem_votes": 16623,
        "rep_votes": 6267,
        "other_votes": 0,
        "total_votes": 22890,
        "dem_candidate": "Connie Pillich",
        "rep_candidate": "Josh Mandel",
        "margin": -10356,
        "margin_pct": -45.242463958060284,
        "winner": "DEM",
        "color": "#2171b5"
      },
      "3": {
        "dem_votes": 15743,
        "rep_votes": 4812,
        "other_votes": 0,
        "total_votes": 20555,
        "dem_candidate": "Connie Pillich",
        "rep_candidate": "Josh Mandel",
        "margin": -10931,
        "margin_pct": -53.17927511554367,
        "winner": "DEM",
        "color": "#2171b5"
      },
      "4": {
        "dem_votes": 16694,
        "rep_votes": 20818,
        "other_votes": 0,
        "total_votes": 37512,
        "dem_candidate": "Connie Pillich",
        "rep_candidate": "Josh Mandel",
        "margin": 4124,
        "margin_pct": 10.993815312433354,
        "winner": "REP",
        "color": "#fb6a4a"
      },
      "5": {
        "dem_votes": 13458,
        "rep_votes": 12130,
        "other_votes": 0,
        "total_votes": 25588,
        "dem_candidate": "Connie Pillich",
        "rep_candidate": "Josh Mandel",
        "margin": -1328,
        "margin_pct": -5.189932780991089,
        "winner": "DEM",
        "color": "#6baed6"
      },
      "6": {
        "dem_votes": 9189,
        "rep_votes": 9800,
        "other_votes": 0,
        "total_votes": 18989,
        "dem_candidate": "Connie Pillich",
        "rep_candidate": "Josh Mandel",
        "margin": 611,
        "margin_pct": 3.2176523250302806,
        "winner": "REP",
        "color": "#fcbba1"
      },
      "7": {
        "dem_votes": 17566,
        "rep_votes": 13179,
        "other_votes": 0,
        "total_votes": 30745,
        "dem_candidate": "Connie Pillich",
        "rep_candidate": "Josh Mandel",
        "margin": -4387,
        "margin_pct": -14.268986827126362,
        "winner": "DEM",
        "color": "#6baed6"
      },
      "8": {
        "dem_votes": 15886,
        "rep_votes": 15013,
        "other_votes": 0,
        "total_votes": 30899,
        "dem_candidate": "Connie Pillich",
        "rep_candidate": "Josh Mandel",
        "margin": -873,
        "margin_pct": -2.825334153208842,
        "winner": "DEM",
        "color": "#c6dbef"
      },
      "9": {
        "dem_votes": 13538,
        "rep_votes": 10165,
        "other_votes": 0,
        "total_votes": 23703,
        "dem_candidate": "Connie Pillich",
        "rep_candidate": "Josh Mandel",
        "margin": -3373,
        "margin_pct": -14.23026621102814,
        "winner": "DEM",
        "color": "#6baed6"
      },
      "10": {
        "dem_votes": 11141,
        "rep_votes": 12941,
        "other_votes": 0,
        "total_votes": 24082,
        "dem_candidate": "Connie Pillich",
        "rep_candidate": "Josh Mandel",
        "margin": 1800,
        "margin_pct": 7.474462253965617,
        "winner": "REP",
        "color": "#fb6a4a"
      },
      "11": {
        "dem_votes": 12348,
        "rep_votes": 17029,
        "other_votes": 0,
        "total_votes": 29377,
        "dem_candidate": "Connie Pillich",
        "rep_candidate": "Josh Mandel",
        "margin": 4681,
        "margin_pct": 15.934234264901113,
        "winner": "REP",
        "color": "#cb181d"
      },
      "12": {
        "dem_votes": 9082,
        "rep_votes": 16816,
        "other_votes": 0,
        "total_votes": 25898,
        "dem_candidate": "Connie Pillich",
        "rep_candidate": "Josh Mandel",
        "margin": 7734,
        "margin_pct": 29.86330990810101,
        "winner": "REP",
        "color": "#cb181d"
      },
      "13": {
        "dem_votes": 14420,
        "rep_votes": 7007,
        "other_votes": 0,
        "total_votes": 21427,
        "dem_candidate": "Connie Pillich",
        "rep_candidate": "Josh Mandel",
        "margin": -7413,
        "margin_pct": -34.59653707938582,
        "winner": "DEM",
        "color": "#2171b5"
      },
      "14": {
        "dem_votes": 11961,
        "rep_votes": 12098,
        "other_votes": 0,
        "total_votes": 24059,
        "dem_candidate": "Connie Pillich",
        "rep_candidate": "Josh Mandel",
        "margin": 137,
        "margin_pct": 0.569433476038073,
        "winner": "REP",
        "color": "#fcbba1"
      },
      "15": {
        "dem_votes": 15434,
        "rep_votes": 15429,
        "other_votes": 0,
        "total_votes": 30863,
        "dem_candidate": "Connie Pillich",
        "rep_candidate": "Josh Mandel",
        "margin": -5,
        "margin_pct": -0.016200628584389073,
        "winner": "DEM",
        "color": "#c6dbef"
      },
      "16": {
        "dem_votes": 18197,
        "rep_votes": 18944,
        "other_votes": 0,
        "total_votes": 37141,
        "dem_candidate": "Connie Pillich",
        "rep_candidate": "Josh Mandel",
        "margin": 747,
        "margin_pct": 2.0112544088742896,
        "winner": "REP",
        "color": "#fcbba1"
      },
      "17": {
        "dem_votes": 14459,
        "rep_votes": 19821,
        "other_votes": 0,
        "total_votes": 34280,
        "dem_candidate": "Connie Pillich",
        "rep_candidate": "Josh Mandel",
        "margin": 5362,
        "margin_pct": 15.641773628938157,
        "winner": "REP",
        "color": "#cb181d"
      },
      "18": {
        "dem_votes": 29945,
        "rep_votes": 5999,
        "other_votes": 0,
        "total_votes": 35944,
        "dem_candidate": "Connie Pillich",
        "rep_candidate": "Josh Mandel",
        "margin": -23946,
        "margin_pct": -66.62029824170934,
        "winner": "DEM",
        "color": "#2171b5"
      },
      "19": {
        "dem_votes": 18394,
        "rep_votes": 20217,
        "other_votes": 0,
        "total_votes": 38611,
        "dem_candidate": "Connie Pillich",
        "rep_candidate": "Josh Mandel",
        "margin": 1823,
        "margin_pct": 4.721452435834348,
        "winner": "REP",
        "color": "#fcbba1"
      },
      "20": {
        "dem_votes": 19430,
        "rep_votes": 3500,
        "other_votes": 0,
        "total_votes": 22930,
        "dem_candidate": "Connie Pillich",
        "rep_candidate": "Josh Mandel",
        "margin": -15930,
        "margin_pct": -69.47230702136939,
        "winner": "DEM",
        "color": "#2171b5"
      },
      "21": {
        "dem_votes": 19630,
        "rep_votes": 9458,
        "other_votes": 0,
        "total_votes": 29088,
        "dem_candidate": "Connie Pillich",
        "rep_candidate": "Josh Mandel",
        "margin": -10172,
        "margin_pct": -34.96974697469747,
        "winner": "DEM",
        "color": "#2171b5"
      },
      "22": {
        "dem_votes": 24054,
        "rep_votes": 6181,
        "other_votes": 0,
        "total_votes": 30235,
        "dem_candidate": "Connie Pillich",
        "rep_candidate": "Josh Mandel",
        "margin": -17873,
        "margin_pct": -59.11361005457252,
        "winner": "DEM",
        "color": "#2171b5"
      },
      "23": {
        "dem_votes": 16534,
        "rep_votes": 20013,
        "other_votes": 0,
        "total_votes": 36547,
        "dem_candidate": "Connie Pillich",
        "rep_candidate": "Josh Mandel",
        "margin": 3479,
        "margin_pct": 9.519249185979698,
        "winner": "REP",
        "color": "#fb6a4a"
      },
      "24": {
        "dem_votes": 11860,
        "rep_votes": 8238,
        "other_votes": 0,
        "total_votes": 20098,
        "dem_candidate": "Connie Pillich",
        "rep_candidate": "Josh Mandel",
        "margin": -3622,
        "margin_pct": -18.021693700865757,
        "winner": "DEM",
        "color": "#2171b5"
      },
      "25": {
        "dem_votes": 18259,
        "rep_votes": 6683,
        "other_votes": 0,
        "total_votes": 24942,
        "dem_candidate": "Connie Pillich",
        "rep_candidate": "Josh Mandel",
        "margin": -11576,
        "margin_pct": -46.411675086199985,
        "winner": "DEM",
        "color": "#2171b5"
      },
      "26": {
        "dem_votes": 19900,
        "rep_votes": 14983,
        "other_votes": 0,
        "total_votes": 34883,
        "dem_candidate": "Connie Pillich",
        "rep_candidate": "Josh Mandel",
        "margin": -4917,
        "margin_pct": -14.09569131095376,
        "winner": "DEM",
        "color": "#6baed6"
      },
      "27": {
        "dem_votes": 18471,
        "rep_votes": 27836,
        "other_votes": 0,
        "total_votes": 46307,
        "dem_candidate": "Connie Pillich",
        "rep_candidate": "Josh Mandel",
        "margin": 9365,
        "margin_pct": 20.22372427494763,
        "winner": "REP",
        "color": "#cb181d"
      },
      "28": {
        "dem_votes": 17299,
        "rep_votes": 22361,
        "other_votes": 0,
        "total_votes": 39660,
        "dem_candidate": "Connie Pillich",
        "rep_candidate": "Josh Mandel",
        "margin": 5062,
        "margin_pct": 12.763489662128089,
        "winner": "REP",
        "color": "#fb6a4a"
      },
      "29": {
        "dem_votes": 11173,
        "rep_votes": 22566,
        "other_votes": 0,
        "total_votes": 33739,
        "dem_candidate": "Connie Pillich",
        "rep_candidate": "Josh Mandel",
        "margin": 11393,
        "margin_pct": 33.768042917691695,
        "winner": "REP",
        "color": "#cb181d"
      },
      "30": {
        "dem_votes": 8115,
        "rep_votes": 30186,
        "other_votes": 0,
        "total_votes": 38301,
        "dem_candidate": "Connie Pillich",
        "rep_candidate": "Josh Mandel",
        "margin": 22071,
        "margin_pct": 57.62512728127203,
        "winner": "REP",
        "color": "#cb181d"
      },
      "31": {
        "dem_votes": 13724,
        "rep_votes": 15632,
        "other_votes": 0,
        "total_votes": 29356,
        "dem_candidate": "Connie Pillich",
        "rep_candidate": "Josh Mandel",
        "margin": 1908,
        "margin_pct": 6.499523095789616,
        "winner": "REP",
        "color": "#fb6a4a"
      },
      "32": {
        "dem_votes": 12492,
        "rep_votes": 13552,
        "other_votes": 0,
        "total_votes": 26044,
        "dem_candidate": "Connie Pillich",
        "rep_candidate": "Josh Mandel",
        "margin": 1060,
        "margin_pct": 4.070035324834895,
        "winner": "REP",
        "color": "#fcbba1"
      },
      "33": {
        "dem_votes": 15969,
        "rep_votes": 6996,
        "other_votes": 0,
        "total_votes": 22965,
        "dem_candidate": "Connie Pillich",
        "rep_candidate": "Josh Mandel",
        "margin": -8973,
        "margin_pct": -39.07250163291966,
        "winner": "DEM",
        "color": "#2171b5"
      },
      "34": {
        "dem_votes": 13054,
        "rep_votes": 14339,
        "other_votes": 0,
        "total_votes": 27393,
        "dem_candidate": "Connie Pillich",
        "rep_candidate": "Josh Mandel",
        "margin": 1285,
        "margin_pct": 4.690979447304056,
        "winner": "REP",
        "color": "#fcbba1"
      },
      "35": {
        "dem_votes": 14561,
        "rep_votes": 18723,
        "other_votes": 0,
        "total_votes": 33284,
        "dem_candidate": "Connie Pillich",
        "rep_candidate": "Josh Mandel",
        "margin": 4162,
        "margin_pct": 12.50450666987141,
        "winner": "REP",
        "color": "#fb6a4a"
      },
      "36": {
        "dem_votes": 13412,
        "rep_votes": 18619,
        "other_votes": 0,
        "total_votes": 32031,
        "dem_candidate": "Connie Pillich",
        "rep_candidate": "Josh Mandel",
        "margin": 5207,
        "margin_pct": 16.25612687708782,
        "winner": "REP",
        "color": "#cb181d"
      },
      "37": {
        "dem_votes": 13435,
        "rep_votes": 22328,
        "other_votes": 0,
        "total_votes": 35763,
        "dem_candidate": "Connie Pillich",
        "rep_candidate": "Josh Mandel",
        "margin": 8893,
        "margin_pct": 24.866482118390515,
        "winner": "REP",
        "color": "#cb181d"
      },
      "38": {
        "dem_votes": 19785,
        "rep_votes": 6685,
        "other_votes": 0,
        "total_votes": 26470,
        "dem_candidate": "Connie Pillich",
        "rep_candidate": "Josh Mandel",
        "margin": -13100,
        "margin_pct": -49.48998866641481,
        "winner": "DEM",
        "color": "#2171b5"
      },
      "39": {
        "dem_votes": 14302,
        "rep_votes": 18731,
        "other_votes": 0,
        "total_votes": 33033,
        "dem_candidate": "Connie Pillich",
        "rep_candidate": "Josh Mandel",
        "margin": 4429,
        "margin_pct": 13.407804316895225,
        "winner": "REP",
        "color": "#fb6a4a"
      },
      "40": {
        "dem_votes": 9045,
        "rep_votes": 23188,
        "other_votes": 0,
        "total_votes": 32233,
        "dem_candidate": "Connie Pillich",
        "rep_candidate": "Josh Mandel",
        "margin": 14143,
        "margin_pct": 43.877392734154434,
        "winner": "REP",
        "color": "#cb181d"
      },
      "41": {
        "dem_votes": 14821,
        "rep_votes": 10938,
        "other_votes": 0,
        "total_votes": 25759,
        "dem_candidate": "Connie Pillich",
        "rep_candidate": "Josh Mandel",
        "margin": -3883,
        "margin_pct": -15.074342948095811,
        "winner": "DEM",
        "color": "#2171b5"
      },
      "42": {
        "dem_votes": 12786,
        "rep_votes": 5265,
        "other_votes": 0,
        "total_votes": 18051,
        "dem_candidate": "Connie Pillich",
        "rep_candidate": "Josh Mandel",
        "margin": -7521,
        "margin_pct": -41.665281701844776,
        "winner": "DEM",
        "color": "#2171b5"
      },
      "43": {
        "dem_votes": 13601,
        "rep_votes": 9147,
        "other_votes": 0,
        "total_votes": 22748,
        "dem_candidate": "Connie Pillich",
        "rep_candidate": "Josh Mandel",
        "margin": -4454,
        "margin_pct": -19.57974327413399,
        "winner": "DEM",
        "color": "#2171b5"
      },
      "44": {
        "dem_votes": 14506,
        "rep_votes": 18407,
        "other_votes": 0,
        "total_votes": 32913,
        "dem_candidate": "Connie Pillich",
        "rep_candidate": "Josh Mandel",
        "margin": 3901,
        "margin_pct": 11.852459514477562,
        "winner": "REP",
        "color": "#fb6a4a"
      },
      "45": {
        "dem_votes": 9233,
        "rep_votes": 23494,
        "other_votes": 0,
        "total_votes": 32727,
        "dem_candidate": "Connie Pillich",
        "rep_candidate": "Josh Mandel",
        "margin": 14261,
        "margin_pct": 43.57564090811868,
        "winner": "REP",
        "color": "#cb181d"
      },
      "46": {
        "dem_votes": 7309,
        "rep_votes": 18266,
        "other_votes": 0,
        "total_votes": 25575,
        "dem_candidate": "Connie Pillich",
        "rep_candidate": "Josh Mandel",
        "margin": 10957,
        "margin_pct": 42.84261974584555,
        "winner": "REP",
        "color": "#cb181d"
      },
      "47": {
        "dem_votes": 7956,
        "rep_votes": 16094,
        "other_votes": 0,
        "total_votes": 24050,
        "dem_candidate": "Connie Pillich",
        "rep_candidate": "Josh Mandel",
        "margin": 8138,
        "margin_pct": 33.83783783783784,
        "winner": "REP",
        "color": "#cb181d"
      },
      "48": {
        "dem_votes": 12451,
        "rep_votes": 21801,
        "other_votes": 0,
        "total_votes": 34252,
        "dem_candidate": "Connie Pillich",
        "rep_candidate": "Josh Mandel",
        "margin": 9350,
        "margin_pct": 27.297676048113978,
        "winner": "REP",
        "color": "#cb181d"
      },
      "49": {
        "dem_votes": 11738,
        "rep_votes": 13764,
        "other_votes": 0,
        "total_votes": 25502,
        "dem_candidate": "Connie Pillich",
        "rep_candidate": "Josh Mandel",
        "margin": 2026,
        "margin_pct": 7.9444749431417145,
        "winner": "REP",
        "color": "#fb6a4a"
      },
      "50": {
        "dem_votes": 13266,
        "rep_votes": 18634,
        "other_votes": 0,
        "total_votes": 31900,
        "dem_candidate": "Connie Pillich",
        "rep_candidate": "Josh Mandel",
        "margin": 5368,
        "margin_pct": 16.82758620689655,
        "winner": "REP",
        "color": "#cb181d"
      },
      "51": {
        "dem_votes": 10600,
        "rep_votes": 19299,
        "other_votes": 0,
        "total_votes": 29899,
        "dem_candidate": "Connie Pillich",
        "rep_candidate": "Josh Mandel",
        "margin": 8699,
        "margin_pct": 29.094618549115353,
        "winner": "REP",
        "color": "#cb181d"
      },
      "52": {
        "dem_votes": 13771,
        "rep_votes": 15981,
        "other_votes": 0,
        "total_votes": 29752,
        "dem_candidate": "Connie Pillich",
        "rep_candidate": "Josh Mandel",
        "margin": 2210,
        "margin_pct": 7.428072062382361,
        "winner": "REP",
        "color": "#fb6a4a"
      },
      "53": {
        "dem_votes": 13506,
        "rep_votes": 13509,
        "other_votes": 0,
        "total_votes": 27015,
        "dem_candidate": "Connie Pillich",
        "rep_candidate": "Josh Mandel",
        "margin": 3,
        "margin_pct": 0.01110494169905608,
        "winner": "REP",
        "color": "#fcbba1"
      },
      "54": {
        "dem_votes": 13180,
        "rep_votes": 19160,
        "other_votes": 0,
        "total_votes": 32340,
        "dem_candidate": "Connie Pillich",
        "rep_candidate": "Josh Mandel",
        "margin": 5980,
        "margin_pct": 18.491032776747062,
        "winner": "REP",
        "color": "#cb181d"
      },
      "55": {
        "dem_votes": 7312,
        "rep_votes": 23568,
        "other_votes": 0,
        "total_votes": 30880,
        "dem_candidate": "Connie Pillich",
        "rep_candidate": "Josh Mandel",
        "margin": 16256,
        "margin_pct": 52.64248704663213,
        "winner": "REP",
        "color": "#cb181d"
      },
      "56": {
        "dem_votes": 7212,
        "rep_votes": 20295,
        "other_votes": 0,
        "total_votes": 27507,
        "dem_candidate": "Connie Pillich",
        "rep_candidate": "Josh Mandel",
        "margin": 13083,
        "margin_pct": 47.56243865197949,
        "winner": "REP",
        "color": "#cb181d"
      },
      "57": {
        "dem_votes": 13457,
        "rep_votes": 22570,
        "other_votes": 0,
        "total_votes": 36027,
        "dem_candidate": "Connie Pillich",
        "rep_candidate": "Josh Mandel",
        "margin": 9113,
        "margin_pct": 25.29491770061343,
        "winner": "REP",
        "color": "#cb181d"
      },
      "58": {
        "dem_votes": 13119,
        "rep_votes": 9452,
        "other_votes": 0,
        "total_votes": 22571,
        "dem_candidate": "Connie Pillich",
        "rep_candidate": "Josh Mandel",
        "margin": -3667,
        "margin_pct": -16.246511009702715,
        "winner": "DEM",
        "color": "#2171b5"
      },
      "59": {
        "dem_votes": 13905,
        "rep_votes": 18608,
        "other_votes": 0,
        "total_votes": 32513,
        "dem_candidate": "Connie Pillich",
        "rep_candidate": "Josh Mandel",
        "margin": 4703,
        "margin_pct": 14.464983237474241,
        "winner": "REP",
        "color": "#fb6a4a"
      },
      "60": {
        "dem_votes": 10835,
        "rep_votes": 19864,
        "other_votes": 0,
        "total_votes": 30699,
        "dem_candidate": "Connie Pillich",
        "rep_candidate": "Josh Mandel",
        "margin": 9029,
        "margin_pct": 29.411381478224047,
        "winner": "REP",
        "color": "#cb181d"
      },
      "61": {
        "dem_votes": 11515,
        "rep_votes": 21548,
        "other_votes": 0,
        "total_votes": 33063,
        "dem_candidate": "Connie Pillich",
        "rep_candidate": "Josh Mandel",
        "margin": 10033,
        "margin_pct": 30.345098750869553,
        "winner": "REP",
        "color": "#cb181d"
      },
      "62": {
        "dem_votes": 7866,
        "rep_votes": 23658,
        "other_votes": 0,
        "total_votes": 31524,
        "dem_candidate": "Connie Pillich",
        "rep_candidate": "Josh Mandel",
        "margin": 15792,
        "margin_pct": 50.095165588123336,
        "winner": "REP",
        "color": "#cb181d"
      },
      "63": {
        "dem_votes": 6330,
        "rep_votes": 20101,
        "other_votes": 0,
        "total_votes": 26431,
        "dem_candidate": "Connie Pillich",
        "rep_candidate": "Josh Mandel",
        "margin": 13771,
        "margin_pct": 52.1016987628164,
        "winner": "REP",
        "color": "#cb181d"
      },
      "64": {
        "dem_votes": 13427,
        "rep_votes": 12811,
        "other_votes": 0,
        "total_votes": 26238,
        "dem_candidate": "Connie Pillich",
        "rep_candidate": "Josh Mandel",
        "margin": -616,
        "margin_pct": -2.3477399192011585,
        "winner": "DEM",
        "color": "#c6dbef"
      },
      "65": {
        "dem_votes": 13829,
        "rep_votes": 18375,
        "other_votes": 0,
        "total_votes": 32204,
        "dem_candidate": "Connie Pillich",
        "rep_candidate": "Josh Mandel",
        "margin": 4546,
        "margin_pct": 14.11625884983232,
        "winner": "REP",
        "color": "#fb6a4a"
      },
      "66": {
        "dem_votes": 11390,
        "rep_votes": 20481,
        "other_votes": 0,
        "total_votes": 31871,
        "dem_candidate": "Connie Pillich",
        "rep_candidate": "Josh Mandel",
        "margin": 9091,
        "margin_pct": 28.524363841737006,
        "winner": "REP",
        "color": "#cb181d"
      },
      "67": {
        "dem_votes": 10053,
        "rep_votes": 19303,
        "other_votes": 0,
        "total_votes": 29356,
        "dem_candidate": "Connie Pillich",
        "rep_candidate": "Josh Mandel",
        "margin": 9250,
        "margin_pct": 31.509742471726394,
        "winner": "REP",
        "color": "#cb181d"
      },
      "68": {
        "dem_votes": 12394,
        "rep_votes": 18058,
        "other_votes": 0,
        "total_votes": 30452,
        "dem_candidate": "Connie Pillich",
        "rep_candidate": "Josh Mandel",
        "margin": 5664,
        "margin_pct": 18.5997635623276,
        "winner": "REP",
        "color": "#cb181d"
      },
      "69": {
        "dem_votes": 11080,
        "rep_votes": 20232,
        "other_votes": 0,
        "total_votes": 31312,
        "dem_candidate": "Connie Pillich",
        "rep_candidate": "Josh Mandel",
        "margin": 9152,
        "margin_pct": 29.22841083290751,
        "winner": "REP",
        "color": "#cb181d"
      },
      "70": {
        "dem_votes": 11139,
        "rep_votes": 22890,
        "other_votes": 0,
        "total_votes": 34029,
        "dem_candidate": "Connie Pillich",
        "rep_candidate": "Josh Mandel",
        "margin": 11751,
        "margin_pct": 34.532310676187954,
        "winner": "REP",
        "color": "#cb181d"
      },
      "71": {
        "dem_votes": 10283,
        "rep_votes": 21582,
        "other_votes": 0,
        "total_votes": 31865,
        "dem_candidate": "Connie Pillich",
        "rep_candidate": "Josh Mandel",
        "margin": 11299,
        "margin_pct": 35.458967519221716,
        "winner": "REP",
        "color": "#cb181d"
      },
      "72": {
        "dem_votes": 14168,
        "rep_votes": 16112,
        "other_votes": 0,
        "total_votes": 30280,
        "dem_candidate": "Connie Pillich",
        "rep_candidate": "Josh Mandel",
        "margin": 1944,
        "margin_pct": 6.420079260237781,
        "winner": "REP",
        "color": "#fb6a4a"
      },
      "73": {
        "dem_votes": 12364,
        "rep_votes": 18551,
        "other_votes": 0,
        "total_votes": 30915,
        "dem_candidate": "Connie Pillich",
        "rep_candidate": "Josh Mandel",
        "margin": 6187,
        "margin_pct": 20.012938702895035,
        "winner": "REP",
        "color": "#cb181d"
      },
      "74": {
        "dem_votes": 10979,
        "rep_votes": 14268,
        "other_votes": 0,
        "total_votes": 25247,
        "dem_candidate": "Connie Pillich",
        "rep_candidate": "Josh Mandel",
        "margin": 3289,
        "margin_pct": 13.027290371133205,
        "winner": "REP",
        "color": "#fb6a4a"
      },
      "75": {
        "dem_votes": 12257,
        "rep_votes": 15876,
        "other_votes": 0,
        "total_votes": 28133,
        "dem_candidate": "Connie Pillich",
        "rep_candidate": "Josh Mandel",
        "margin": 3619,
        "margin_pct": 12.863896491664592,
        "winner": "REP",
        "color": "#fb6a4a"
      },
      "76": {
        "dem_votes": 11089,
        "rep_votes": 21135,
        "other_votes": 0,
        "total_votes": 32224,
        "dem_candidate": "Connie Pillich",
        "rep_candidate": "Josh Mandel",
        "margin": 10046,
        "margin_pct": 31.175521350546177,
        "winner": "REP",
        "color": "#cb181d"
      },
      "77": {
        "dem_votes": 7003,
        "rep_votes": 15922,
        "other_votes": 0,
        "total_votes": 22925,
        "dem_candidate": "Connie Pillich",
        "rep_candidate": "Josh Mandel",
        "margin": 8919,
        "margin_pct": 38.905125408942205,
        "winner": "REP",
        "color": "#cb181d"
      },
      "78": {
        "dem_votes": 8478,
        "rep_votes": 22471,
        "other_votes": 0,
        "total_votes": 30949,
        "dem_candidate": "Connie Pillich",
        "rep_candidate": "Josh Mandel",
        "margin": 13993,
        "margin_pct": 45.21309250702769,
        "winner": "REP",
        "color": "#cb181d"
      },
      "79": {
        "dem_votes": 9479,
        "rep_votes": 18827,
        "other_votes": 0,
        "total_votes": 28306,
        "dem_candidate": "Connie Pillich",
        "rep_candidate": "Josh Mandel",
        "margin": 9348,
        "margin_pct": 33.02480039567583,
        "winner": "REP",
        "color": "#cb181d"
      },
      "80": {
        "dem_votes": 9535,
        "rep_votes": 26000,
        "other_votes": 0,
        "total_votes": 35535,
        "dem_candidate": "Connie Pillich",
        "rep_candidate": "Josh Mandel",
        "margin": 16465,
        "margin_pct": 46.33459969044604,
        "winner": "REP",
        "color": "#cb181d"
      },
      "81": {
        "dem_votes": 9341,
        "rep_votes": 19259,
        "other_votes": 0,
        "total_votes": 28600,
        "dem_candidate": "Connie Pillich",
        "rep_candidate": "Josh Mandel",
        "margin": 9918,
        "margin_pct": 34.67832167832168,
        "winner": "REP",
        "color": "#cb181d"
      },
      "82": {
        "dem_votes": 8792,
        "rep_votes": 22888,
        "other_votes": 0,
        "total_votes": 31680,
        "dem_candidate": "Connie Pillich",
        "rep_candidate": "Josh Mandel",
        "margin": 14096,
        "margin_pct": 44.494949494949495,
        "winner": "REP",
        "color": "#cb181d"
      },
      "83": {
        "dem_votes": 8620,
        "rep_votes": 22833,
        "other_votes": 0,
        "total_votes": 31453,
        "dem_candidate": "Connie Pillich",
        "rep_candidate": "Josh Mandel",
        "margin": 14213,
        "margin_pct": 45.188058372810225,
        "winner": "REP",
        "color": "#cb181d"
      },
      "84": {
        "dem_votes": 7308,
        "rep_votes": 24583,
        "other_votes": 0,
        "total_votes": 31891,
        "dem_candidate": "Connie Pillich",
        "rep_candidate": "Josh Mandel",
        "margin": 17275,
        "margin_pct": 54.168887773980124,
        "winner": "REP",
        "color": "#cb181d"
      },
      "85": {
        "dem_votes": 8912,
        "rep_votes": 23298,
        "other_votes": 0,
        "total_votes": 32210,
        "dem_candidate": "Connie Pillich",
        "rep_candidate": "Josh Mandel",
        "margin": 14386,
        "margin_pct": 44.66314809065508,
        "winner": "REP",
        "color": "#cb181d"
      },
      "86": {
        "dem_votes": 6734,
        "rep_votes": 13380,
        "other_votes": 0,
        "total_votes": 20114,
        "dem_candidate": "Connie Pillich",
        "rep_candidate": "Josh Mandel",
        "margin": 6646,
        "margin_pct": 33.04166252361539,
        "winner": "REP",
        "color": "#cb181d"
      },
      "87": {
        "dem_votes": 9056,
        "rep_votes": 18904,
        "other_votes": 0,
        "total_votes": 27960,
        "dem_candidate": "Connie Pillich",
        "rep_candidate": "Josh Mandel",
        "margin": 9848,
        "margin_pct": 35.22174535050072,
        "winner": "REP",
        "color": "#cb181d"
      },
      "88": {
        "dem_votes": 12184,
        "rep_votes": 18256,
        "other_votes": 0,
        "total_votes": 30440,
        "dem_candidate": "Connie Pillich",
        "rep_candidate": "Josh Mandel",
        "margin": 6072,
        "margin_pct": 19.947437582128778,
        "winner": "REP",
        "color": "#cb181d"
      },
      "89": {
        "dem_votes": 16062,
        "rep_votes": 20548,
        "other_votes": 0,
        "total_votes": 36610,
        "dem_candidate": "Connie Pillich",
        "rep_candidate": "Josh Mandel",
        "margin": 4486,
        "margin_pct": 12.253482655012292,
        "winner": "REP",
        "color": "#fb6a4a"
      },
      "90": {
        "dem_votes": 10465,
        "rep_votes": 17630,
        "other_votes": 0,
        "total_votes": 28095,
        "dem_candidate": "Connie Pillich",
        "rep_candidate": "Josh Mandel",
        "margin": 7165,
        "margin_pct": 25.50275849795337,
        "winner": "REP",
        "color": "#cb181d"
      },
      "91": {
        "dem_votes": 8279,
        "rep_votes": 17672,
        "other_votes": 0,
        "total_votes": 25951,
        "dem_candidate": "Connie Pillich",
        "rep_candidate": "Josh Mandel",
        "margin": 9393,
        "margin_pct": 36.195136988940696,
        "winner": "REP",
        "color": "#cb181d"
      },
      "92": {
        "dem_votes": 10918,
        "rep_votes": 15403,
        "other_votes": 0,
        "total_votes": 26321,
        "dem_candidate": "Connie Pillich",
        "rep_candidate": "Josh Mandel",
        "margin": 4485,
        "margin_pct": 17.039626154021505,
        "winner": "REP",
        "color": "#cb181d"
      },
      "93": {
        "dem_votes": 9185,
        "rep_votes": 17714,
        "other_votes": 0,
        "total_votes": 26899,
        "dem_candidate": "Connie Pillich",
        "rep_candidate": "Josh Mandel",
        "margin": 8529,
        "margin_pct": 31.70749842001561,
        "winner": "REP",
        "color": "#cb181d"
      },
      "94": {
        "dem_votes": 13052,
        "rep_votes": 19353,
        "other_votes": 0,
        "total_votes": 32405,
        "dem_candidate": "Connie Pillich",
        "rep_candidate": "Josh Mandel",
        "margin": 6301,
        "margin_pct": 19.44453016509798,
        "winner": "REP",
        "color": "#cb181d"
      },
      "95": {
        "dem_votes": 12240,
        "rep_votes": 16184,
        "other_votes": 0,
        "total_votes": 28424,
        "dem_candidate": "Connie Pillich",
        "rep_candidate": "Josh Mandel",
        "margin": 3944,
        "margin_pct": 13.875598086124402,
        "winner": "REP",
        "color": "#fb6a4a"
      },
      "96": {
        "dem_votes": 14173,
        "rep_votes": 17371,
        "other_votes": 0,
        "total_votes": 31544,
        "dem_candidate": "Connie Pillich",
        "rep_candidate": "Josh Mandel",
        "margin": 3198,
        "margin_pct": 10.13821962972356,
        "winner": "REP",
        "color": "#fb6a4a"
      },
      "97": {
        "dem_votes": 10472,
        "rep_votes": 17443,
        "other_votes": 0,
        "total_votes": 27915,
        "dem_candidate": "Connie Pillich",
        "rep_candidate": "Josh Mandel",
        "margin": 6971,
        "margin_pct": 24.972237148486474,
        "winner": "REP",
        "color": "#cb181d"
      },
      "98": {
        "dem_votes": 7661,
        "rep_votes": 16577,
        "other_votes": 0,
        "total_votes": 24238,
        "dem_candidate": "Connie Pillich",
        "rep_candidate": "Josh Mandel",
        "margin": 8916,
        "margin_pct": 36.78521330142751,
        "winner": "REP",
        "color": "#cb181d"
      },
      "99": {
        "dem_votes": 14677,
        "rep_votes": 22166,
        "other_votes": 0,
        "total_votes": 36843,
        "dem_candidate": "Connie Pillich",
        "rep_candidate": "Josh Mandel",
        "margin": 7489,
        "margin_pct": 20.326792063621312,
        "winner": "REP",
        "color": "#cb181d"
      }
    }
  }
}
