{
  "scope": "state_senate",
  "contest_type": "attorney_general",
  "year": 2008,
  "general": {
    "results": {
      "1": {
        "dem_votes": 47482,
        "rep_votes": 59651,
        "other_votes": 6525,
        "total_votes": 113658,
        "dem_candidate": "Richard Cordray",
        "rep_candidate": "Mike Crites",
        "margin": 12169,
        "margin_pct": 10.70668144785233,
        "winner": "REP",
        "color": "#fb6a4a"
      },
      "2": {
        "dem_votes": 79670,
        "rep_votes": 57096,
        "other_votes": 7459,
        "total_votes": 144225,
        "dem_candidate": "Richard Cordray",
        "rep_candidate": "Mike Crites",
        "margin": -22574,
        "margin_pct": -15.651932743976428,
        "winner": "DEM",
        "color": "#2171b5"
      },
      "3": {
        "dem_votes": 57878,
        "rep_votes": 25850,
        "other_votes": 3074,
        "total_votes": 86802,
        "dem_candidate": "Richard Cordray",
        "rep_candidate": "Mike Crites",
        "margin": -32028,
        "margin_pct": -36.89776733254994,
        "winner": "DEM",
        "color": "#2171b5"
      },
      "4": {
        "dem_votes": 58192,
        "rep_votes": 76271,
        "other_votes": 6933,
        "total_votes": 141396,
        "dem_candidate": "Richard Cordray",
        "rep_candidate": "Mike Crites",
        "margin": 18079,
        "margin_pct": 12.786075985176385,
        "winner": "REP",
        "color": "#fb6a4a"
      },
      "5": {
        "dem_votes": 31217,
        "rep_votes": 44729,
        "other_votes": 4575,
        "total_votes": 80521,
        "dem_candidate": "Richard Cordray",
        "rep_candidate": "Mike Crites",
        "margin": 13512,
        "margin_pct": 16.780715589721936,
        "winner": "REP",
        "color": "#cb181d"
      },
      "7": {
        "dem_votes": 11865,
        "rep_votes": 8234,
        "other_votes": 1004,
        "total_votes": 21103,
        "dem_candidate": "Richard Cordray",
        "rep_candidate": "Mike Crites",
        "margin": -3631,
        "margin_pct": -17.206084442970194,
        "winner": "DEM",
        "color": "#2171b5"
      },
      "8": {
        "dem_votes": 47828,
        "rep_votes": 63400,
        "other_votes": 6098,
        "total_votes": 117326,
        "dem_candidate": "Richard Cordray",
        "rep_candidate": "Mike Crites",
        "margin": 15572,
        "margin_pct": 13.27242043536812,
        "winner": "REP",
        "color": "#fb6a4a"
      },
      "9": {
        "dem_votes": 51930,
        "rep_votes": 16700,
        "other_votes": 4398,
        "total_votes": 73028,
        "dem_candidate": "Richard Cordray",
        "rep_candidate": "Mike Crites",
        "margin": -35230,
        "margin_pct": -48.24177027989264,
        "winner": "DEM",
        "color": "#2171b5"
      },
      "10": {
        "dem_votes": 54294,
        "rep_votes": 55247,
        "other_votes": 5772,
        "total_votes": 115313,
        "dem_candidate": "Richard Cordray",
        "rep_candidate": "Mike Crites",
        "margin": 953,
        "margin_pct": 0.8264462809917356,
        "winner": "REP",
        "color": "#fcbba1"
      },
      "11": {
        "dem_votes": 47115,
        "rep_votes": 19349,
        "other_votes": 3534,
        "total_votes": 69998,
        "dem_candidate": "Richard Cordray",
        "rep_candidate": "Mike Crites",
        "margin": -27766,
        "margin_pct": -39.66684762421783,
        "winner": "DEM",
        "color": "#2171b5"
      },
      "12": {
        "dem_votes": 54719,
        "rep_votes": 78419,
        "other_votes": 7502,
        "total_votes": 140640,
        "dem_candidate": "Richard Cordray",
        "rep_candidate": "Mike Crites",
        "margin": 23700,
        "margin_pct": 16.851535836177476,
        "winner": "REP",
        "color": "#cb181d"
      },
      "13": {
        "dem_votes": 3224,
        "rep_votes": 3241,
        "other_votes": 484,
        "total_votes": 6949,
        "dem_candidate": "Richard Cordray",
        "rep_candidate": "Mike Crites",
        "margin": 17,
        "margin_pct": 0.24463951647719098,
        "winner": "REP",
        "color": "#fcbba1"
      },
      "14": {
        "dem_votes": 55906,
        "rep_votes": 64898,
        "other_votes": 7450,
        "total_votes": 128254,
        "dem_candidate": "Richard Cordray",
        "rep_candidate": "Mike Crites",
        "margin": 8992,
        "margin_pct": 7.011087373493225,
        "winner": "REP",
        "color": "#fb6a4a"
      },
      "15": {
        "dem_votes": 92165,
        "rep_votes": 24197,
        "other_votes": 4056,
        "total_votes": 120418,
        "dem_candidate": "Richard Cordray",
        "rep_candidate": "Mike Crites",
        "margin": -67968,
        "margin_pct": -56.44338886213025,
        "winner": "DEM",
        "color": "#2171b5"
      },
      "16": {
        "dem_votes": 80871,
        "rep_votes": 55870,
        "other_votes": 4411,
        "total_votes": 141152,
        "dem_candidate": "Richard Cordray",
        "rep_candidate": "Mike Crites",
        "margin": -25001,
        "margin_pct": -17.712111766039445,
        "winner": "DEM",
        "color": "#2171b5"
      },
      "17": {
        "dem_votes": 56672,
        "rep_votes": 45102,
        "other_votes": 7671,
        "total_votes": 109445,
        "dem_candidate": "Richard Cordray",
        "rep_candidate": "Mike Crites",
        "margin": -11570,
        "margin_pct": -10.57151994152314,
        "winner": "DEM",
        "color": "#6baed6"
      },
      "18": {
        "dem_votes": 29850,
        "rep_votes": 18411,
        "other_votes": 1556,
        "total_votes": 49817,
        "dem_candidate": "Richard Cordray",
        "rep_candidate": "Mike Crites",
        "margin": -11439,
        "margin_pct": -22.962041070317362,
        "winner": "DEM",
        "color": "#2171b5"
      },
      "19": {
        "dem_votes": 54350,
        "rep_votes": 63043,
        "other_votes": 6018,
        "total_votes": 123411,
        "dem_candidate": "Richard Cordray",
        "rep_candidate": "Mike Crites",
        "margin": 8693,
        "margin_pct": 7.043942598309713,
        "winner": "REP",
        "color": "#fb6a4a"
      },
      "20": {
        "dem_votes": 60422,
        "rep_votes": 54529,
        "other_votes": 10108,
        "total_votes": 125059,
        "dem_candidate": "Richard Cordray",
        "rep_candidate": "Mike Crites",
        "margin": -5893,
        "margin_pct": -4.712175852997385,
        "winner": "DEM",
        "color": "#c6dbef"
      },
      "21": {
        "dem_votes": 106165,
        "rep_votes": 14577,
        "other_votes": 4319,
        "total_votes": 125061,
        "dem_candidate": "Richard Cordray",
        "rep_candidate": "Mike Crites",
        "margin": -91588,
        "margin_pct": -73.23466148519523,
        "winner": "DEM",
        "color": "#2171b5"
      },
      "22": {
        "dem_votes": 56114,
        "rep_votes": 49408,
        "other_votes": 5506,
        "total_votes": 111028,
        "dem_candidate": "Richard Cordray",
        "rep_candidate": "Mike Crites",
        "margin": -6706,
        "margin_pct": -6.039917858558201,
        "winner": "DEM",
        "color": "#6baed6"
      },
      "23": {
        "dem_votes": 64881,
        "rep_votes": 10982,
        "other_votes": 3757,
        "total_votes": 79620,
        "dem_candidate": "Richard Cordray",
        "rep_candidate": "Mike Crites",
        "margin": -53899,
        "margin_pct": -67.69530268776688,
        "winner": "DEM",
        "color": "#2171b5"
      },
      "24": {
        "dem_votes": 64211,
        "rep_votes": 36711,
        "other_votes": 4646,
        "total_votes": 105568,
        "dem_candidate": "Richard Cordray",
        "rep_candidate": "Mike Crites",
        "margin": -27500,
        "margin_pct": -26.049560472870564,
        "winner": "DEM",
        "color": "#2171b5"
      },
      "25": {
        "dem_votes": 88514,
        "rep_votes": 29098,
        "other_votes": 4146,
        "total_votes": 121758,
        "dem_candidate": "Richard Cordray",
        "rep_candidate": "Mike Crites",
        "margin": -59416,
        "margin_pct": -48.79843624238243,
        "winner": "DEM",
        "color": "#2171b5"
      },
      "26": {
        "dem_votes": 39232,
        "rep_votes": 33131,
        "other_votes": 5568,
        "total_votes": 77931,
        "dem_candidate": "Richard Cordray",
        "rep_candidate": "Mike Crites",
        "margin": -6101,
        "margin_pct": -7.8287202781948135,
        "winner": "DEM",
        "color": "#6baed6"
      },
      "29": {
        "dem_votes": 74400,
        "rep_votes": 47287,
        "other_votes": 5710,
        "total_votes": 127397,
        "dem_candidate": "Richard Cordray",
        "rep_candidate": "Mike Crites",
        "margin": -27113,
        "margin_pct": -21.282290791776887,
        "winner": "DEM",
        "color": "#2171b5"
      },
      "30": {
        "dem_votes": 75027,
        "rep_votes": 45315,
        "other_votes": 6625,
        "total_votes": 126967,
        "dem_candidate": "Richard Cordray",
        "rep_candidate": "Mike Crites",
        "margin": -29712,
        "margin_pct": -23.401356257925286,
        "winner": "DEM",
        "color": "#2171b5"
      },
      "31": {
        "dem_votes": 63997,
        "rep_votes": 51147,
        "other_votes": 6214,
        "total_votes": 121358,
        "dem_candidate": "Richard Cordray",
        "rep_candidate": "Mike Crites",
        "margin": -12850,
        "margin_pct": -10.588506732147861,
        "winner": "DEM",
        "color": "#6baed6"
      },
      "32": {
        "dem_votes": 76193,
        "rep_votes": 40080,
        "other_votes": 6692,
        "total_votes": 122965,
        "dem_candidate": "Richard Cordray",
        "rep_candidate": "Mike Crites",
        "margin": -36113,
        "margin_pct": -29.368519497417967,
        "winner": "DEM",
        "color": "#2171b5"
      },
      "33": {
        "dem_votes": 86420,
        "rep_votes": 38832,
        "other_votes": 6735,
        "total_votes": 131987,
        "dem_candidate": "Richard Cordray",
        "rep_candidate": "Mike Crites",
        "margin": -47588,
        "margin_pct": -36.055066029230154,
        "winner": "DEM",
        "color": "#2171b5"
      }
    }
  }
}
