{
  "scope": "state_senate",
  "contest_type": "chief_justice_of_the_supreme_court_term_commencing_01_01",
  "year": 2004,
  "general": {
    "results": {
      "1": {
        "dem_votes": 36539,
        "rep_votes": 61575,
        "other_votes": 0,
        "total_votes": 98114,
        "dem_candidate": "C. Ellen Connally",
        "rep_candidate": "Thomas J. Moyer",
        "margin": 25036,
        "margin_pct": 25.517255437552233,
        "winner": "REP",
        "color": "#cb181d"
      },
      "2": {
        "dem_votes": 46750,
        "rep_votes": 65639,
        "other_votes": 0,
        "total_votes": 112389,
        "dem_candidate": "C. Ellen Connally",
        "rep_candidate": "Thomas J. Moyer",
        "margin": 18889,
        "margin_pct": 16.80680493642616,
        "winner": "REP",
        "color": "#cb181d"
      },
      "3": {
        "dem_votes": 34663,
        "rep_votes": 45411,
        "other_votes": 0,
        "total_votes": 80074,
        "dem_candidate": "C. Ellen Connally",
        "rep_candidate": "Thomas J. Moyer",
        "margin": 10748,
        "margin_pct": 13.42258410969853,
        "winner": "REP",
        "color": "#fb6a4a"
      },
      "4": {
        "dem_votes": 55432,
        "rep_votes": 62262,
        "other_votes": 0,
        "total_votes": 117694,
        "dem_candidate": "C. Ellen Connally",
        "rep_candidate": "Thomas J. Moyer",
        "margin": 6830,
        "margin_pct": 5.80318452937278,
        "winner": "REP",
        "color": "#fb6a4a"
      },
      "5": {
        "dem_votes": 48738,
        "rep_votes": 65614,
        "other_votes": 0,
        "total_votes": 114352,
        "dem_candidate": "C. Ellen Connally",
        "rep_candidate": "Thomas J. Moyer",
        "margin": 16876,
        "margin_pct": 14.757940394571149,
        "winner": "REP",
        "color": "#fb6a4a"
      },
      "6": {
        "dem_votes": 40599,
        "rep_votes": 41010,
        "other_votes": 0,
        "total_votes": 81609,
        "dem_candidate": "C. Ellen Connally",
        "rep_candidate": "Thomas J. Moyer",
        "margin": 411,
        "margin_pct": 0.5036209241627762,
        "winner": "REP",
        "color": "#fcbba1"
      },
      "7": {
        "dem_votes": 42028,
        "rep_votes": 61846,
        "other_votes": 0,
        "total_votes": 103874,
        "dem_candidate": "C. Ellen Connally",
        "rep_candidate": "Thomas J. Moyer",
        "margin": 19818,
        "margin_pct": 19.078884032577932,
        "winner": "REP",
        "color": "#cb181d"
      },
      "8": {
        "dem_votes": 38184,
        "rep_votes": 55852,
        "other_votes": 0,
        "total_votes": 94036,
        "dem_candidate": "C. Ellen Connally",
        "rep_candidate": "Thomas J. Moyer",
        "margin": 17668,
        "margin_pct": 18.788549066315028,
        "winner": "REP",
        "color": "#cb181d"
      },
      "9": {
        "dem_votes": 40531,
        "rep_votes": 25875,
        "other_votes": 0,
        "total_votes": 66406,
        "dem_candidate": "C. Ellen Connally",
        "rep_candidate": "Thomas J. Moyer",
        "margin": -14656,
        "margin_pct": -22.07029485287474,
        "winner": "DEM",
        "color": "#2171b5"
      },
      "10": {
        "dem_votes": 51330,
        "rep_votes": 65362,
        "other_votes": 0,
        "total_votes": 116692,
        "dem_candidate": "C. Ellen Connally",
        "rep_candidate": "Thomas J. Moyer",
        "margin": 14032,
        "margin_pct": 12.024817468206903,
        "winner": "REP",
        "color": "#fb6a4a"
      },
      "11": {
        "dem_votes": 47358,
        "rep_votes": 35393,
        "other_votes": 0,
        "total_votes": 82751,
        "dem_candidate": "C. Ellen Connally",
        "rep_candidate": "Thomas J. Moyer",
        "margin": -11965,
        "margin_pct": -14.459039769912147,
        "winner": "DEM",
        "color": "#6baed6"
      },
      "12": {
        "dem_votes": 45800,
        "rep_votes": 67958,
        "other_votes": 0,
        "total_votes": 113758,
        "dem_candidate": "C. Ellen Connally",
        "rep_candidate": "Thomas J. Moyer",
        "margin": 22158,
        "margin_pct": 19.4781905448408,
        "winner": "REP",
        "color": "#cb181d"
      },
      "13": {
        "dem_votes": 48795,
        "rep_votes": 54303,
        "other_votes": 0,
        "total_votes": 103098,
        "dem_candidate": "C. Ellen Connally",
        "rep_candidate": "Thomas J. Moyer",
        "margin": 5508,
        "margin_pct": 5.3424896700226965,
        "winner": "REP",
        "color": "#fb6a4a"
      },
      "14": {
        "dem_votes": 45423,
        "rep_votes": 61587,
        "other_votes": 0,
        "total_votes": 107010,
        "dem_candidate": "C. Ellen Connally",
        "rep_candidate": "Thomas J. Moyer",
        "margin": 16164,
        "margin_pct": 15.105130361648445,
        "winner": "REP",
        "color": "#cb181d"
      },
      "15": {
        "dem_votes": 48666,
        "rep_votes": 32432,
        "other_votes": 0,
        "total_votes": 81098,
        "dem_candidate": "C. Ellen Connally",
        "rep_candidate": "Thomas J. Moyer",
        "margin": -16234,
        "margin_pct": -20.01775629485314,
        "winner": "DEM",
        "color": "#2171b5"
      },
      "16": {
        "dem_votes": 33354,
        "rep_votes": 54557,
        "other_votes": 0,
        "total_votes": 87911,
        "dem_candidate": "C. Ellen Connally",
        "rep_candidate": "Thomas J. Moyer",
        "margin": 21203,
        "margin_pct": 24.118710969048244,
        "winner": "REP",
        "color": "#cb181d"
      },
      "17": {
        "dem_votes": 45563,
        "rep_votes": 56797,
        "other_votes": 0,
        "total_votes": 102360,
        "dem_candidate": "C. Ellen Connally",
        "rep_candidate": "Thomas J. Moyer",
        "margin": 11234,
        "margin_pct": 10.974990230558813,
        "winner": "REP",
        "color": "#fb6a4a"
      },
      "18": {
        "dem_votes": 44465,
        "rep_votes": 46344,
        "other_votes": 0,
        "total_votes": 90809,
        "dem_candidate": "C. Ellen Connally",
        "rep_candidate": "Thomas J. Moyer",
        "margin": 1879,
        "margin_pct": 2.069178165159841,
        "winner": "REP",
        "color": "#fcbba1"
      },
      "19": {
        "dem_votes": 34693,
        "rep_votes": 59407,
        "other_votes": 0,
        "total_votes": 94100,
        "dem_candidate": "C. Ellen Connally",
        "rep_candidate": "Thomas J. Moyer",
        "margin": 24714,
        "margin_pct": 26.263549415515406,
        "winner": "REP",
        "color": "#cb181d"
      },
      "20": {
        "dem_votes": 40236,
        "rep_votes": 63597,
        "other_votes": 0,
        "total_votes": 103833,
        "dem_candidate": "C. Ellen Connally",
        "rep_candidate": "Thomas J. Moyer",
        "margin": 23361,
        "margin_pct": 22.498627603940943,
        "winner": "REP",
        "color": "#cb181d"
      },
      "21": {
        "dem_votes": 67445,
        "rep_votes": 31655,
        "other_votes": 0,
        "total_votes": 99100,
        "dem_candidate": "C. Ellen Connally",
        "rep_candidate": "Thomas J. Moyer",
        "margin": -35790,
        "margin_pct": -36.115035317860745,
        "winner": "DEM",
        "color": "#2171b5"
      },
      "22": {
        "dem_votes": 39681,
        "rep_votes": 53722,
        "other_votes": 0,
        "total_votes": 93403,
        "dem_candidate": "C. Ellen Connally",
        "rep_candidate": "Thomas J. Moyer",
        "margin": 14041,
        "margin_pct": 15.032707728873804,
        "winner": "REP",
        "color": "#cb181d"
      },
      "23": {
        "dem_votes": 59219,
        "rep_votes": 34550,
        "other_votes": 0,
        "total_votes": 93769,
        "dem_candidate": "C. Ellen Connally",
        "rep_candidate": "Thomas J. Moyer",
        "margin": -24669,
        "margin_pct": -26.308268190979962,
        "winner": "DEM",
        "color": "#2171b5"
      },
      "24": {
        "dem_votes": 42926,
        "rep_votes": 38562,
        "other_votes": 0,
        "total_votes": 81488,
        "dem_candidate": "C. Ellen Connally",
        "rep_candidate": "Thomas J. Moyer",
        "margin": -4364,
        "margin_pct": -5.355389750638131,
        "winner": "DEM",
        "color": "#6baed6"
      },
      "25": {
        "dem_votes": 32672,
        "rep_votes": 39130,
        "other_votes": 0,
        "total_votes": 71802,
        "dem_candidate": "C. Ellen Connally",
        "rep_candidate": "Thomas J. Moyer",
        "margin": 6458,
        "margin_pct": 8.994178435141082,
        "winner": "REP",
        "color": "#fb6a4a"
      },
      "26": {
        "dem_votes": 40689,
        "rep_votes": 65934,
        "other_votes": 0,
        "total_votes": 106623,
        "dem_candidate": "C. Ellen Connally",
        "rep_candidate": "Thomas J. Moyer",
        "margin": 25245,
        "margin_pct": 23.676880222841227,
        "winner": "REP",
        "color": "#cb181d"
      },
      "27": {
        "dem_votes": 55126,
        "rep_votes": 59677,
        "other_votes": 0,
        "total_votes": 114803,
        "dem_candidate": "C. Ellen Connally",
        "rep_candidate": "Thomas J. Moyer",
        "margin": 4551,
        "margin_pct": 3.964182120676289,
        "winner": "REP",
        "color": "#fcbba1"
      },
      "28": {
        "dem_votes": 43607,
        "rep_votes": 46496,
        "other_votes": 0,
        "total_votes": 90103,
        "dem_candidate": "C. Ellen Connally",
        "rep_candidate": "Thomas J. Moyer",
        "margin": 2889,
        "margin_pct": 3.2063305328346448,
        "winner": "REP",
        "color": "#fcbba1"
      },
      "29": {
        "dem_votes": 49477,
        "rep_votes": 69966,
        "other_votes": 0,
        "total_votes": 119443,
        "dem_candidate": "C. Ellen Connally",
        "rep_candidate": "Thomas J. Moyer",
        "margin": 20489,
        "margin_pct": 17.153788836516163,
        "winner": "REP",
        "color": "#cb181d"
      },
      "30": {
        "dem_votes": 52939,
        "rep_votes": 55013,
        "other_votes": 0,
        "total_votes": 107952,
        "dem_candidate": "C. Ellen Connally",
        "rep_candidate": "Thomas J. Moyer",
        "margin": 2074,
        "margin_pct": 1.9212242478138433,
        "winner": "REP",
        "color": "#fcbba1"
      },
      "31": {
        "dem_votes": 44085,
        "rep_votes": 65780,
        "other_votes": 0,
        "total_votes": 109865,
        "dem_candidate": "C. Ellen Connally",
        "rep_candidate": "Thomas J. Moyer",
        "margin": 21695,
        "margin_pct": 19.746962180858326,
        "winner": "REP",
        "color": "#cb181d"
      },
      "32": {
        "dem_votes": 52945,
        "rep_votes": 57075,
        "other_votes": 0,
        "total_votes": 110020,
        "dem_candidate": "C. Ellen Connally",
        "rep_candidate": "Thomas J. Moyer",
        "margin": 4130,
        "margin_pct": 3.7538629340119978,
        "winner": "REP",
        "color": "#fcbba1"
      },
      "33": {
        "dem_votes": 51912,
        "rep_votes": 55495,
        "other_votes": 0,
        "total_votes": 107407,
        "dem_candidate": "C. Ellen Connally",
        "rep_candidate": "Thomas J. Moyer",
        "margin": 3583,
        "margin_pct": 3.3359092051728467,
        "winner": "REP",
        "color": "#fcbba1"
      }
    }
  }
}
